Workbook

Sheet Read Me
A1: Real-Time Fund Explanation: SIP Growth, Direct vs Regular, Tax & Exit Load
A2: Companion model for the Mutual Funds team presentation — Jan 2025 to Dec 2034
A4: WHAT THIS WORKBOOK SHOWS
A5: Three real, currently-traded Indian mutual fund schemes across three risk categories (Flexi Cap, Mid Cap, Small Cap) are used to
A6: demonstrate, with a single consistent SIP plan, how Direct vs Regular plans, expense ratio, exit load and capital-gains tax actually
A7: affect what an investor takes home — not just the headline NAV growth.
A9: THE SCENARIO MODELLED
A10: • SIP starts 1-Jan-2025, runs for 10 years (120 months) to Dec-2034.
A11: • SIP amount starts at ₹3,000/month and steps up by ₹1,000/month every 12 months (Year 1 = ₹3,000, Year 2 = ₹4,000 … Year 10 = ₹12,000).
A12: • A full withdrawal / redemption check is modelled as of 15-Jan-2036 — i.e. ~11 years after the SIP started, about 13 months after the
A13: 120th and final instalment (Dec-2034) — to show what an investor actually takes home at the end of the full journey.
A14: • Every SIP instalment is a separate purchase (“lot”) with its own purchase date and NAV — this is exactly how AMCs and the
... A45: • This is an educational illustration only — not investment advice and not a return guarantee.

Sheet Fund Facts
A1: Fund Facts — Real, Current Data (cited)
A2: Verify NAV/AUM/expense ratio again on the day you present — these change daily/quarterly
A4: Fund | B4: Category | C4: Plan | D4: NAV (₹) | E4: NAV as of | F4: AUM (₹ Cr) | G4: Expense Ratio | H4: Exit Load | I4: 5Y CAGR (historical, Direct) | J4: Source
A5: Parag Parikh Flexi Cap Fund | B5: Flexi Cap | C5: Direct | D5: 89.86 | E5: 18-Sep-2026 | F5: 147405 | G5: 0.0053 | H5: 2% if <365 days; 1% if 366–730 days; Nil after 730 days (first 10% of units per purchase exempt) | I5: 0.1127 | J5: Value Research / Tickertape
A6: Parag Parikh Flexi Cap Fund | B6: Flexi Cap | C6: Regular | D6: 83.92 | E6: 31-Jul-2026 | F6: 143388 | G6: 0.0105 | H6: Same as Direct plan | I6: — (see Assumptions sheet) | J6: Value Research
A7: HDFC Mid-Cap Opportunities Fund | B7: Mid Cap | C7: Direct | D7: 228.61 | E7: 22-Jul-2026 | F7: 100858 | G7: 0.0061 | H7: 1% if redeemed within 365 days; Nil after | I7: ~26.5% (3Y CAGR) | J7: Value Research / ClearTax
A8: HDFC Mid-Cap Opportunities Fund | B8: Mid Cap | C8: Regular | D8: 202.65 | E8: 6-Feb-2026 | F8: 105143 | G8: 0.0109 | H8: Same as Direct plan | I8: — (see Assumptions sheet) | J8: ClearTax / Value Research
A9: SBI Small Cap Fund | B9: Small Cap | C9: Direct | D9: 206.81 | E9: 9-Jul-2026 | F9: 37395 | G9: 0.0074 | H9: 1% if redeemed within 365 days; Nil after | I9: 0.1548 | J9: Upstox / ClearTax
A10: SBI Small Cap Fund | B10: Small Cap | C10: Regular | D10: 181.56 | E10: 15-Jul-2026 | F10: 40157 | G10: 0.0153 | H10: Same as Direct plan | I10: — (see Assumptions sheet) | J10: MySIPonline / ClearTax
A12: Note: All figures above are real, sourced figures as of the dates shown — refresh from the AMC factsheet / Value Research / AMFI before presenting live.

Sheet Assumptions
A1: Assumptions — edit any blue cell
A2: Everything else in this workbook recalculates from these inputs
A3: SIP & TAX-DATE INPUTS
A4: SIP Start Date | C4: 45658
A5: Withdrawal Check Date (case study) | C5: 49689 | D5: Used only in the Withdrawal_Jan2036 sheet — by this date all 120 SIP instalments (Jan-2025 to Dec-2034) are complete
A6: SIP Base Amount — Year 1 (₹/month) | C6: 3000
A7: Annual Step-Up (₹/month, added every 12 months) | C7: 1000
A8: Investment Horizon (years) | C8: 10
A10: TAX INPUTS (equity mutual funds, current rules)
A11: STCG Tax Rate (holding ≤ 12 months) | C11: 0.2
A12: LTCG Tax Rate (holding > 12 months, on gains above exemption) | C12: 0.125
A13: LTCG Exemption (₹, aggregate per investor per FY, all equity LTCG) | C13: 125000
A15: FUND PROJECTION ASSUMPTIONS
A16: Starting NAV (Jan-2025) is an illustrative back-estimate for this model, not an audited historical NAV. Direct-plan CAGR is an illustrative assumption; Regular-plan CAGR = Direct CAGR − (Regular expense ratio − Direct expense ratio) — same portfolio, only cost differs.
A18: Fund | B18: Plan | C18: Category | D18: Starting NAV (Jan-2025, illustrative) | E18: Expense Ratio (from Fund Facts) | F18: Assumed Annual Return (CAGR) | G18: Exit Load <365 days | H18: Exit Load 365–730 days | I18: Exit Load >730 days
A19: Parag Parikh Flexi Cap Fund | B19: Direct | C19: Flexi Cap | D19: 75 | E19: ='Fund Facts'!G5 -> 0.0053 | F19: 0.12 | G19: 0.02 | H19: 0.01 | I19: 0
A20: Parag Parikh Flexi Cap Fund | B20: Regular | C20: Flexi Cap | D20: 70 | E20: ='Fund Facts'!G6 -> 0.0105 | F20: =F19-(E20-E19) -> 0.1148 | G20: 0.02 | H20: 0.01 | I20: 0
A21: HDFC Mid-Cap Opportunities Fund | B21: Direct | C21: Mid Cap | D21: 190 | E21: ='Fund Facts'!G7 -> 0.0061 | F21: 0.14 | G21: 0.01 | H21: 0 | I21: 0
A22: HDFC Mid-Cap Opportunities Fund | B22: Regular | C22: Mid Cap | D22: 168 | E22: ='Fund Facts'!G8 -> 0.0109 | F22: =F21-(E22-E21) -> 0.1352 | G22: 0.01 | H22: 0 | I22: 0
A23: SBI Small Cap Fund | B23: Direct | C23: Small Cap | D23: 170 | E23: ='Fund Facts'!G9 -> 0.0074 | F23: 0.15 | G23: 0.01 | H23: 0 | I23: 0
A24: SBI Small Cap Fund | B24: Regular | C24: Small Cap | D24: 149 | E24: ='Fund Facts'!G10 -> 0.0153 | F24: =F23-(E24-E23) -> 0.1421 | G24: 0.01 | H24: 0 | I24: 0
A26: STP & SWP ASSUMPTIONS
A27: STP moves a lumpsum from a debt/liquid fund into Fund 1 (Parag Parikh Flexi Cap, Direct) in equal monthly instalments. SWP draws a fixed monthly amount from the Fund 1 Direct corpus once the 10-year SIP ends.
A28: STP — Lumpsum Amount (₹) | C28: 500000
A29: STP — Duration (months) | C29: 10
A30: STP — Start Date | C30: 45658
A31: STP — Source Fund Assumed Annual Return (liquid/ultra-short debt) | C31: 0.065
A32: SWP — Monthly Withdrawal Amount (₹) | C32: 25000
A33: SWP — Start Date | C33: 49310 | D33: Starts the month after the 10-year SIP ends (Dec-2034)
A34: SWP — Duration (months) | C34: 60
A35: SWP — Assumed Annual Return (post-SIP phase, Fund 1 Direct) | C35: 0.12 | D35: Can differ from the accumulation-phase CAGR — many investors de-risk at/after this stage

Sheet SIP_Fund1_PPFAS
A1: SIP Schedule — Parag Parikh Flexi Cap Fund
A2: Jan-2025 to Dec-2034 · 120 monthly instalments · Direct vs Regular side by side
A4: Month # | B4: Date | C4: SIP Amount (₹) | D4: NAV — Direct (₹) | E4: Units — Direct | F4: Cum. Units — Direct | G4: Value — Direct (₹) | H4: NAV — Regular (₹) | I4: Units — Regular | J4: Cum. Units — Regular | K4: Value — Regular (₹) | L4: Cum. Invested (₹)
A5: 1 | B5: =Assumptions!$C$4 -> 45658 | C5: =Assumptions!$C$6+(YEAR(B5)-YEAR(Assumptions!$C$4))*Assumptions!$C$7 -> 3000 | D5: =Assumptions!$D$19*(1+Assumptions!$F$19)^((B5-Assumptions!$C$4)/365) -> 75 | E5: =C5/D5 -> 40 | F5: =E5 -> 40 | G5: =F5*D5 -> 3000 | H5: =Assumptions!$D$20*(1+Assumptions!$F$20)^((B5-Assumptions!$C$4)/365) -> 70 | I5: =C5/H5 -> 42.857143 | J5: =I5 -> 42.857143 | K5: =J5*H5 -> 3000 | L5: =C5 -> 3000
A6: 2 | B6: =EDATE(B5,1) -> 45689 | C6: =Assumptions!$C$6+(YEAR(B6)-YEAR(Assumptions!$C$4))*Assumptions!$C$7 -> 3000 | D6: =Assumptions!$D$19*(1+Assumptions!$F$19)^((B6-Assumptions!$C$4)/365) -> 75.725374 | E6: =C6/D6 -> 39.61684 | F6: =F5+E6 -> 79.61684 | G6: =F6*D6 -> 6029.0149 | H6: =Assumptions!$D$20*(1+Assumptions!$F$20)^((B6-Assumptions!$C$4)/365) -> 70.649086 | I6: =C6/H6 -> 42.463394 | J6: =J5+I6 -> 85.320537 | K6: =J6*H6 -> 6027.818 | L6: =L5+C6 -> 6000
A7: 3 | B7: =EDATE(B6,1) -> 45717 | C7: =Assumptions!$C$6+(YEAR(B7)-YEAR(Assumptions!$C$4))*Assumptions!$C$7 -> 3000 | D7: =Assumptions!$D$19*(1+Assumptions!$F$19)^((B7-Assumptions!$C$4)/365) -> 76.386578 | E7: =C7/D7 -> 39.273915 | F7: =F6+E7 -> 118.89076 | G7: =F7*D7 -> 9081.6579 | H7: =Assumptions!$D$20*(1+Assumptions!$F$20)^((B7-Assumptions!$C$4)/365) -> 71.240529 | I7: =C7/H7 -> 42.110861 | J7: =J6+I7 -> 127.4314 | K7: =J7*H7 -> 9078.2802 | L7: =L6+C7 -> 9000
A8: 4 | B8: =EDATE(B7,1) -> 45748 | C8: =Assumptions!$C$6+(YEAR(B8)-YEAR(Assumptions!$C$4))*Assumptions!$C$7 -> 3000 | D8: =Assumptions!$D$19*(1+Assumptions!$F$19)^((B8-Assumptions!$C$4)/365) -> 77.125362 | E8: =C8/D8 -> 38.897711 | F8: =F7+E8 -> 157.78847 | G8: =F8*D8 -> 12169.493 | H8: =Assumptions!$D$20*(1+Assumptions!$F$20)^((B8-Assumptions!$C$4)/365) -> 71.901119 | I8: =C8/H8 -> 41.723968 | J8: =J7+I8 -> 169.15537 | K8: =J8*H8 -> 12162.46 | L8: =L7+C8 -> 12000
A9: 5 | B9: =EDATE(B8,1) -> 45778 | C9: =Assumptions!$C$6+(YEAR(B9)-YEAR(Assumptions!$C$4))*Assumptions!$C$7 -> 3000 | D9: =Assumptions!$D$19*(1+Assumptions!$F$19)^((B9-Assumptions!$C$4)/365) -> 77.847117 | E9: =C9/D9 -> 38.537073 | F9: =F8+E9 -> 196.32554 | G9: =F9*D9 -> 15283.377 | H9: =Assumptions!$D$20*(1+Assumptions!$F$20)^((B9-Assumptions!$C$4)/365) -> 72.54623 | I9: =C9/H9 -> 41.352941 | J9: =J8+I9 -> 210.50831 | K9: =J9*H9 -> 15271.584 | L9: =L8+C9 -> 15000
A10: 6 | B10: =EDATE(B9,1) -> 45809 | C10: =Assumptions!$C$6+(YEAR(B10)-YEAR(Assumptions!$C$4))*Assumptions!$C$7 -> 3000 | D10: =Assumptions!$D$19*(1+Assumptions!$F$19)^((B10-Assumptions!$C$4)/365) -> 78.600026 | E10: =C10/D10 -> 38.167926 | F10: =F9+E10 -> 234.49346 | G10: =F10*D10 -> 18431.193 | H10: =Assumptions!$D$20*(1+Assumptions!$F$20)^((B10-Assumptions!$C$4)/365) -> 73.218927 | I10: =C10/H10 -> 40.973013 | J10: =J9+I10 -> 251.48132 | K10: =J10*H10 -> 18413.192 | L10: =L9+C10 -> 18000
A11: 7 | B11: =EDATE(B10,1) -> 45839 | C11: =Assumptions!$C$6+(YEAR(B11)-YEAR(Assumptions!$C$4))*Assumptions!$C$7 -> 3000 | D11: =Assumptions!$D$19*(1+Assumptions!$F$19)^((B11-Assumptions!$C$4)/365) -> 79.335581 | E11: =C11/D11 -> 37.814055 | F11: =F10+E11 -> 272.30752 | G11: =F11*D11 -> 21603.675 | H11: =Assumptions!$D$20*(1+Assumptions!$F$20)^((B11-Assumptions!$C$4)/365) -> 73.875862 | I11: =C11/H11 -> 40.608663 | J11: =J10+I11 -> 292.08998 | K11: =J11*H11 -> 21578.399 | L11: =L10+C11 -> 21000
A12: 8 | B12: =EDATE(B11,1) -> 45870 | C12: =Assumptions!$C$6+(YEAR(B12)-YEAR(Assumptions!$C$4))*Assumptions!$C$7 -> 3000 | D12: =Assumptions!$D$19*(1+Assumptions!$F$19)^((B12-Assumptions!$C$4)/365) -> 80.102887 | E12: =C12/D12 -> 37.451834 | F12: =F11+E12 -> 309.75935 | G12: =F12*D12 -> 24812.619 | H12: =Assumptions!$D$20*(1+Assumptions!$F$20)^((B12-Assumptions!$C$4)/365) -> 74.560888 | I12: =C12/H12 -> 40.235573 | J12: =J11+I12 -> 332.32556 | K12: =J12*H12 -> 24778.488 | L12: =L11+C12 -> 24000
A13: 9 | B13: =EDATE(B12,1) -> 45901 | C13: =Assumptions!$C$6+(YEAR(B13)-YEAR(Assumptions!$C$4))*Assumptions!$C$7 -> 3000 | D13: =Assumptions!$D$19*(1+Assumptions!$F$19)^((B13-Assumptions!$C$4)/365) -> 80.877614 | E13: =C13/D13 -> 37.093082 | F13: =F12+E13 -> 346.85244 | G13: =F13*D13 -> 28052.597 | H13: =Assumptions!$D$20*(1+Assumptions!$F$20)^((B13-Assumptions!$C$4)/365) -> 75.252265 | I13: =C13/H13 -> 39.86591 | J13: =J12+I13 -> 372.19147 | K13: =J13*H13 -> 28008.251 | L13: =L12+C13 -> 27000
A14: 10 | B14: =EDATE(B13,1) -> 45931 | C14: =Assumptions!$C$6+(YEAR(B14)-YEAR(Assumptions!$C$4))*Assumptions!$C$7 -> 3000 | D14: =Assumptions!$D$19*(1+Assumptions!$F$19)^((B14-Assumptions!$C$4)/365) -> 81.634483 | E14: =C14/D14 -> 36.749176 | F14: =F13+E14 -> 383.60161 | G14: =F14*D14 -> 31315.119 | H14: =Assumptions!$D$20*(1+Assumptions!$F$20)^((B14-Assumptions!$C$4)/365) -> 75.927444 | I14: =C14/H14 -> 39.511405 | J14: =J13+I14 -> 411.70287 | K14: =J14*H14 -> 31259.547 | L14: =L13+C14 -> 30000
A15: 11 | B15: =EDATE(B14,1) -> 45962 | C15: =Assumptions!$C$6+(YEAR(B15)-YEAR(Assumptions!$C$4))*Assumptions!$C$7 -> 3000 | D15: =Assumptions!$D$19*(1+Assumptions!$F$19)^((B15-Assumptions!$C$4)/365) -> 82.424023 | E15: =C15/D15 -> 36.397156 | F15: =F14+E15 -> 419.99877 | G15: =F15*D15 -> 34617.988 | H15: =Assumptions!$D$20*(1+Assumptions!$F$20)^((B15-Assumptions!$C$4)/365) -> 76.631493 | I15: =C15/H15 -> 39.148395 | J15: =J14+I15 -> 450.85127 | K15: =J15*H15 -> 34549.406 | L15: =L14+C15 -> 33000
A16: 12 | B16: =EDATE(B15,1) -> 45992 | C16: =Assumptions!$C$6+(YEAR(B16)-YEAR(Assumptions!$C$4))*Assumptions!$C$7 -> 3000 | D16: =Assumptions!$D$19*(1+Assumptions!$F$19)^((B16-Assumptions!$C$4)/365) -> 83.195364 | E16: =C16/D16 -> 36.059702 | F16: =F15+E16 -> 456.05847 | G16: =F16*D16 -> 37941.95 | H16: =Assumptions!$D$20*(1+Assumptions!$F$20)^((B16-Assumptions!$C$4)/365) -> 77.319047 | I16: =C16/H16 -> 38.800271 | J16: =J15+I16 -> 489.65154 | K16: =J16*H16 -> 37859.39 | L16: =L15+C16 -> 36000
A17: 13 | B17: =EDATE(B16,1) -> 46023 | C17: =Assumptions!$C$6+(YEAR(B17)-YEAR(Assumptions!$C$4))*Assumptions!$C$7 -> 4000 | D17: =Assumptions!$D$19*(1+Assumptions!$F$19)^((B17-Assumptions!$C$4)/365) -> 84 | E17: =C17/D17 -> 47.619048 | F17: =F16+E17 -> 503.67752 | G17: =F17*D17 -> 42308.911 | H17: =Assumptions!$D$20*(1+Assumptions!$F$20)^((B17-Assumptions!$C$4)/365) -> 78.036 | I17: =C17/H17 -> 51.258394 | J17: =J16+I17 -> 540.90993 | K17: =J17*H17 -> 42210.447 | L17: =L16+C17 -> 40000
... A124: 120 | B124: =EDATE(B123,1) -> 49279 | C124: =Assumptions!$C$6+(YEAR(B124)-YEAR(Assumptions!$C$4))*Assumptions!$C$7 -> 12000 | D124: =Assumptions!$D$19*(1+Assumptions!$F$19)^((B124-Assumptions!$C$4)/365) -> 230.8506 | E124: =C124/D124 -> 51.98167 | F124: =F123+E124 -> 6332.5271 | G124: =F124*D124 -> 1461867.7 | H124: =Assumptions!$D$20*(1+Assumptions!$F$20)^((B124-Assumptions!$C$4)/365) -> 205.73953 | I124: =C124/H124 -> 58.326176 | J124: =J123+I124 -> 6951.9231 | K124: =J124*H124 -> 1430285.4 | L124: =L123+C124 -> 900000
B126: 10-YEAR TOTALS → | G126: =G124 -> 1461867.7 | K126: =K124 -> 1430285.4 | L126: =L124 -> 900000

Sheet SIP_Fund2_HDFCMidcap
A1: SIP Schedule — HDFC Mid-Cap Opportunities Fund
A2: Jan-2025 to Dec-2034 · 120 monthly instalments · Direct vs Regular side by side
A4: Month # | B4: Date | C4: SIP Amount (₹) | D4: NAV — Direct (₹) | E4: Units — Direct | F4: Cum. Units — Direct | G4: Value — Direct (₹) | H4: NAV — Regular (₹) | I4: Units — Regular | J4: Cum. Units — Regular | K4: Value — Regular (₹) | L4: Cum. Invested (₹)
A5: 1 | B5: =Assumptions!$C$4 -> 45658 | C5: =Assumptions!$C$6+(YEAR(B5)-YEAR(Assumptions!$C$4))*Assumptions!$C$7 -> 3000 | D5: =Assumptions!$D$21*(1+Assumptions!$F$21)^((B5-Assumptions!$C$4)/365) -> 190 | E5: =C5/D5 -> 15.789474 | F5: =E5 -> 15.789474 | G5: =F5*D5 -> 3000 | H5: =Assumptions!$D$22*(1+Assumptions!$F$22)^((B5-Assumptions!$C$4)/365) -> 168 | I5: =C5/H5 -> 17.857143 | J5: =I5 -> 17.857143 | K5: =J5*H5 -> 3000 | L5: =C5 -> 3000
A6: 2 | B6: =EDATE(B5,1) -> 45689 | C6: =Assumptions!$C$6+(YEAR(B6)-YEAR(Assumptions!$C$4))*Assumptions!$C$7 -> 3000 | D6: =Assumptions!$D$21*(1+Assumptions!$F$21)^((B6-Assumptions!$C$4)/365) -> 192.12621 | E6: =C6/D6 -> 15.614736 | F6: =F5+E6 -> 31.404209 | G6: =F6*D6 -> 6033.5717 | H6: =Assumptions!$D$22*(1+Assumptions!$F$22)^((B6-Assumptions!$C$4)/365) -> 169.81915 | I6: =C6/H6 -> 17.665852 | J6: =J5+I6 -> 35.522995 | K6: =J6*H6 -> 6032.4848 | L6: =L5+C6 -> 6000
A7: 3 | B7: =EDATE(B6,1) -> 45717 | C7: =Assumptions!$C$6+(YEAR(B7)-YEAR(Assumptions!$C$4))*Assumptions!$C$7 -> 3000 | D7: =Assumptions!$D$21*(1+Assumptions!$F$21)^((B7-Assumptions!$C$4)/365) -> 194.0671 | E7: =C7/D7 -> 15.458571 | F7: =F6+E7 -> 46.86278 | G7: =F7*D7 -> 9094.5239 | H7: =Assumptions!$D$22*(1+Assumptions!$F$22)^((B7-Assumptions!$C$4)/365) -> 171.47918 | I7: =C7/H7 -> 17.494835 | J7: =J6+I7 -> 53.01783 | K7: =J7*H7 -> 9091.454 | L7: =L6+C7 -> 9000
A8: 4 | B8: =EDATE(B7,1) -> 45748 | C8: =Assumptions!$C$6+(YEAR(B8)-YEAR(Assumptions!$C$4))*Assumptions!$C$7 -> 3000 | D8: =Assumptions!$D$21*(1+Assumptions!$F$21)^((B8-Assumptions!$C$4)/365) -> 196.23882 | E8: =C8/D8 -> 15.287495 | F8: =F7+E8 -> 62.150275 | G8: =F8*D8 -> 12196.297 | H8: =Assumptions!$D$22*(1+Assumptions!$F$22)^((B8-Assumptions!$C$4)/365) -> 173.336 | I8: =C8/H8 -> 17.307426 | J8: =J7+I8 -> 70.325256 | K8: =J8*H8 -> 12189.899 | L8: =L7+C8 -> 12000
A9: 5 | B9: =EDATE(B8,1) -> 45778 | C9: =Assumptions!$C$6+(YEAR(B9)-YEAR(Assumptions!$C$4))*Assumptions!$C$7 -> 3000 | D9: =Assumptions!$D$21*(1+Assumptions!$F$21)^((B9-Assumptions!$C$4)/365) -> 198.36363 | E9: =C9/D9 -> 15.12374 | F9: =F8+E9 -> 77.274015 | G9: =F9*D9 -> 15328.354 | H9: =Assumptions!$D$22*(1+Assumptions!$F$22)^((B9-Assumptions!$C$4)/365) -> 175.15207 | I9: =C9/H9 -> 17.127974 | J9: =J8+I9 -> 87.45323 | K9: =J9*H9 -> 15317.614 | L9: =L8+C9 -> 15000
A10: 6 | B10: =EDATE(B9,1) -> 45809 | C10: =Assumptions!$C$6+(YEAR(B10)-YEAR(Assumptions!$C$4))*Assumptions!$C$7 -> 3000 | D10: =Assumptions!$D$21*(1+Assumptions!$F$21)^((B10-Assumptions!$C$4)/365) -> 200.58343 | E10: =C10/D10 -> 14.95637 | F10: =F9+E10 -> 92.230385 | G10: =F10*D10 -> 18499.887 | H10: =Assumptions!$D$22*(1+Assumptions!$F$22)^((B10-Assumptions!$C$4)/365) -> 177.04866 | I10: =C10/H10 -> 16.944494 | J10: =J9+I10 -> 104.39772 | K10: =J10*H10 -> 18483.477 | L10: =L9+C10 -> 18000
A11: 7 | B11: =EDATE(B10,1) -> 45839 | C11: =Assumptions!$C$6+(YEAR(B11)-YEAR(Assumptions!$C$4))*Assumptions!$C$7 -> 3000 | D11: =Assumptions!$D$21*(1+Assumptions!$F$21)^((B11-Assumptions!$C$4)/365) -> 202.75528 | E11: =C11/D11 -> 14.796162 | F11: =F10+E11 -> 107.02655 | G11: =F11*D11 -> 21700.197 | H11: =Assumptions!$D$22*(1+Assumptions!$F$22)^((B11-Assumptions!$C$4)/365) -> 178.90363 | I11: =C11/H11 -> 16.768805 | J11: =J10+I11 -> 121.16653 | K11: =J11*H11 -> 21677.132 | L11: =L10+C11 -> 21000
A12: 8 | B12: =EDATE(B11,1) -> 45870 | C12: =Assumptions!$C$6+(YEAR(B12)-YEAR(Assumptions!$C$4))*Assumptions!$C$7 -> 3000 | D12: =Assumptions!$D$21*(1+Assumptions!$F$21)^((B12-Assumptions!$C$4)/365) -> 205.02423 | E12: =C12/D12 -> 14.632417 | F12: =F11+E12 -> 121.65896 | G12: =F12*D12 -> 24943.035 | H12: =Assumptions!$D$22*(1+Assumptions!$F$22)^((B12-Assumptions!$C$4)/365) -> 180.84085 | I12: =C12/H12 -> 16.589173 | J12: =J11+I12 -> 137.7557 | K12: =J12*H12 -> 24911.857 | L12: =L11+C12 -> 24000
A13: 9 | B13: =EDATE(B12,1) -> 45901 | C13: =Assumptions!$C$6+(YEAR(B13)-YEAR(Assumptions!$C$4))*Assumptions!$C$7 -> 3000 | D13: =Assumptions!$D$21*(1+Assumptions!$F$21)^((B13-Assumptions!$C$4)/365) -> 207.31857 | E13: =C13/D13 -> 14.470484 | F13: =F12+E13 -> 136.12945 | G13: =F13*D13 -> 28222.162 | H13: =Assumptions!$D$22*(1+Assumptions!$F$22)^((B13-Assumptions!$C$4)/365) -> 182.79904 | I13: =C13/H13 -> 16.411465 | J13: =J12+I13 -> 154.16717 | K13: =J13*H13 -> 28181.61 | L13: =L12+C13 -> 27000
A14: 10 | B14: =EDATE(B13,1) -> 45931 | C14: =Assumptions!$C$6+(YEAR(B14)-YEAR(Assumptions!$C$4))*Assumptions!$C$7 -> 3000 | D14: =Assumptions!$D$21*(1+Assumptions!$F$21)^((B14-Assumptions!$C$4)/365) -> 209.56334 | E14: =C14/D14 -> 14.315481 | F14: =F13+E14 -> 150.44493 | G14: =F14*D14 -> 31527.742 | H14: =Assumptions!$D$22*(1+Assumptions!$F$22)^((B14-Assumptions!$C$4)/365) -> 184.71425 | I14: =C14/H14 -> 16.241302 | J14: =J13+I14 -> 170.40847 | K14: =J14*H14 -> 31476.873 | L14: =L13+C14 -> 30000
A15: 11 | B15: =EDATE(B14,1) -> 45962 | C15: =Assumptions!$C$6+(YEAR(B15)-YEAR(Assumptions!$C$4))*Assumptions!$C$7 -> 3000 | D15: =Assumptions!$D$21*(1+Assumptions!$F$21)^((B15-Assumptions!$C$4)/365) -> 211.90848 | E15: =C15/D15 -> 14.157055 | F15: =F14+E15 -> 164.60198 | G15: =F15*D15 -> 34880.555 | H15: =Assumptions!$D$22*(1+Assumptions!$F$22)^((B15-Assumptions!$C$4)/365) -> 186.71439 | I15: =C15/H15 -> 16.067321 | J15: =J14+I15 -> 186.47579 | K15: =J15*H15 -> 34817.713 | L15: =L14+C15 -> 33000
A16: 12 | B16: =EDATE(B15,1) -> 45992 | C16: =Assumptions!$C$6+(YEAR(B16)-YEAR(Assumptions!$C$4))*Assumptions!$C$7 -> 3000 | D16: =Assumptions!$D$21*(1+Assumptions!$F$21)^((B16-Assumptions!$C$4)/365) -> 214.20295 | E16: =C16/D16 -> 14.00541 | F16: =F15+E16 -> 178.60739 | G16: =F16*D16 -> 38258.23 | H16: =Assumptions!$D$22*(1+Assumptions!$F$22)^((B16-Assumptions!$C$4)/365) -> 188.67062 | I16: =C16/H16 -> 15.900727 | J16: =J15+I16 -> 202.37652 | K16: =J16*H16 -> 38182.503 | L16: =L15+C16 -> 36000
A17: 13 | B17: =EDATE(B16,1) -> 46023 | C17: =Assumptions!$C$6+(YEAR(B17)-YEAR(Assumptions!$C$4))*Assumptions!$C$7 -> 4000 | D17: =Assumptions!$D$21*(1+Assumptions!$F$21)^((B17-Assumptions!$C$4)/365) -> 216.6 | E17: =C17/D17 -> 18.467221 | F17: =F16+E17 -> 197.07461 | G17: =F17*D17 -> 42686.362 | H17: =Assumptions!$D$22*(1+Assumptions!$F$22)^((B17-Assumptions!$C$4)/365) -> 190.7136 | I17: =C17/H17 -> 20.973858 | J17: =J16+I17 -> 223.35037 | K17: =J17*H17 -> 42595.954 | L17: =L16+C17 -> 40000
... A124: 120 | B124: =EDATE(B123,1) -> 49279 | C124: =Assumptions!$C$6+(YEAR(B124)-YEAR(Assumptions!$C$4))*Assumptions!$C$7 -> 12000 | D124: =Assumptions!$D$21*(1+Assumptions!$F$21)^((B124-Assumptions!$C$4)/365) -> 697.07725 | E124: =C124/D124 -> 17.214735 | F124: =F123+E124 -> 2282.285 | G124: =F124*D124 -> 1590928.9 | H124: =Assumptions!$D$22*(1+Assumptions!$F$22)^((B124-Assumptions!$C$4)/365) -> 591.09528 | I124: =C124/H124 -> 20.301296 | J124: =J123+I124 -> 2637.1707 | K124: =J124*H124 -> 1558819.2 | L124: =L123+C124 -> 900000
B126: 10-YEAR TOTALS → | G126: =G124 -> 1590928.9 | K126: =K124 -> 1558819.2 | L126: =L124 -> 900000

Sheet SIP_Fund3_SBISmallcap
A1: SIP Schedule — SBI Small Cap Fund
A2: Jan-2025 to Dec-2034 · 120 monthly instalments · Direct vs Regular side by side
A4: Month # | B4: Date | C4: SIP Amount (₹) | D4: NAV — Direct (₹) | E4: Units — Direct | F4: Cum. Units — Direct | G4: Value — Direct (₹) | H4: NAV — Regular (₹) | I4: Units — Regular | J4: Cum. Units — Regular | K4: Value — Regular (₹) | L4: Cum. Invested (₹)
A5: 1 | B5: =Assumptions!$C$4 -> 45658 | C5: =Assumptions!$C$6+(YEAR(B5)-YEAR(Assumptions!$C$4))*Assumptions!$C$7 -> 3000 | D5: =Assumptions!$D$23*(1+Assumptions!$F$23)^((B5-Assumptions!$C$4)/365) -> 170 | E5: =C5/D5 -> 17.647059 | F5: =E5 -> 17.647059 | G5: =F5*D5 -> 3000 | H5: =Assumptions!$D$24*(1+Assumptions!$F$24)^((B5-Assumptions!$C$4)/365) -> 149 | I5: =C5/H5 -> 20.134228 | J5: =I5 -> 20.134228 | K5: =J5*H5 -> 3000 | L5: =C5 -> 3000
A6: 2 | B6: =EDATE(B5,1) -> 45689 | C6: =Assumptions!$C$6+(YEAR(B6)-YEAR(Assumptions!$C$4))*Assumptions!$C$7 -> 3000 | D6: =Assumptions!$D$23*(1+Assumptions!$F$23)^((B6-Assumptions!$C$4)/365) -> 172.02996 | E6: =C6/D6 -> 17.438823 | F6: =F5+E6 -> 35.085882 | G6: =F6*D6 -> 6035.8228 | H6: =Assumptions!$D$24*(1+Assumptions!$F$24)^((B6-Assumptions!$C$4)/365) -> 150.69095 | I6: =C6/H6 -> 19.908296 | J6: =J5+I6 -> 40.042524 | K6: =J6*H6 -> 6034.0459 | L6: =L5+C6 -> 6000
A7: 3 | B7: =EDATE(B6,1) -> 45717 | C7: =Assumptions!$C$6+(YEAR(B7)-YEAR(Assumptions!$C$4))*Assumptions!$C$7 -> 3000 | D7: =Assumptions!$D$23*(1+Assumptions!$F$23)^((B7-Assumptions!$C$4)/365) -> 173.88429 | E7: =C7/D7 -> 17.252852 | F7: =F6+E7 -> 52.338734 | G7: =F7*D7 -> 9100.8838 | H7: =Assumptions!$D$24*(1+Assumptions!$F$24)^((B7-Assumptions!$C$4)/365) -> 152.23475 | I7: =C7/H7 -> 19.706408 | J7: =J6+I7 -> 59.748932 | K7: =J7*H7 -> 9095.8635 | L7: =L6+C7 -> 9000
A8: 4 | B8: =EDATE(B7,1) -> 45748 | C8: =Assumptions!$C$6+(YEAR(B8)-YEAR(Assumptions!$C$4))*Assumptions!$C$7 -> 3000 | D8: =Assumptions!$D$23*(1+Assumptions!$F$23)^((B8-Assumptions!$C$4)/365) -> 175.96063 | E8: =C8/D8 -> 17.049268 | F8: =F7+E8 -> 69.388002 | G8: =F8*D8 -> 12209.557 | H8: =Assumptions!$D$24*(1+Assumptions!$F$24)^((B8-Assumptions!$C$4)/365) -> 153.9624 | I8: =C8/H8 -> 19.485276 | J8: =J7+I8 -> 79.234208 | K8: =J8*H8 -> 12199.089 | L8: =L7+C8 -> 12000
A9: 5 | B9: =EDATE(B8,1) -> 45778 | C9: =Assumptions!$C$6+(YEAR(B9)-YEAR(Assumptions!$C$4))*Assumptions!$C$7 -> 3000 | D9: =Assumptions!$D$23*(1+Assumptions!$F$23)^((B9-Assumptions!$C$4)/365) -> 177.9936 | E9: =C9/D9 -> 16.854539 | F9: =F8+E9 -> 86.242541 | G9: =F9*D9 -> 15350.62 | H9: =Assumptions!$D$24*(1+Assumptions!$F$24)^((B9-Assumptions!$C$4)/365) -> 155.653 | I9: =C9/H9 -> 19.273641 | J9: =J8+I9 -> 98.507849 | K9: =J9*H9 -> 15333.042 | L9: =L8+C9 -> 15000
A10: 6 | B10: =EDATE(B9,1) -> 45809 | C10: =Assumptions!$C$6+(YEAR(B10)-YEAR(Assumptions!$C$4))*Assumptions!$C$7 -> 3000 | D10: =Assumptions!$D$23*(1+Assumptions!$F$23)^((B10-Assumptions!$C$4)/365) -> 180.119 | E10: =C10/D10 -> 16.655655 | F10: =F9+E10 -> 102.8982 | G10: =F10*D10 -> 18533.921 | H10: =Assumptions!$D$24*(1+Assumptions!$F$24)^((B10-Assumptions!$C$4)/365) -> 157.41945 | I10: =C10/H10 -> 19.057366 | J10: =J9+I10 -> 117.56522 | K10: =J10*H10 -> 18507.051 | L10: =L9+C10 -> 18000
A11: 7 | B11: =EDATE(B10,1) -> 45839 | C11: =Assumptions!$C$6+(YEAR(B11)-YEAR(Assumptions!$C$4))*Assumptions!$C$7 -> 3000 | D11: =Assumptions!$D$23*(1+Assumptions!$F$23)^((B11-Assumptions!$C$4)/365) -> 182.20001 | E11: =C11/D11 -> 16.465422 | F11: =F10+E11 -> 119.36362 | G11: =F11*D11 -> 21748.053 | H11: =Assumptions!$D$24*(1+Assumptions!$F$24)^((B11-Assumptions!$C$4)/365) -> 159.148 | I11: =C11/H11 -> 18.850378 | J11: =J10+I11 -> 136.41559 | K11: =J11*H11 -> 21710.269 | L11: =L10+C11 -> 21000
A12: 8 | B12: =EDATE(B11,1) -> 45870 | C12: =Assumptions!$C$6+(YEAR(B12)-YEAR(Assumptions!$C$4))*Assumptions!$C$7 -> 3000 | D12: =Assumptions!$D$23*(1+Assumptions!$F$23)^((B12-Assumptions!$C$4)/365) -> 184.37565 | E12: =C12/D12 -> 16.271129 | F12: =F11+E12 -> 135.63475 | G12: =F12*D12 -> 25007.744 | H12: =Assumptions!$D$24*(1+Assumptions!$F$24)^((B12-Assumptions!$C$4)/365) -> 160.95412 | I12: =C12/H12 -> 18.638852 | J12: =J11+I12 -> 155.05445 | K12: =J12*H12 -> 24956.651 | L12: =L11+C12 -> 24000
A13: 9 | B13: =EDATE(B12,1) -> 45901 | C13: =Assumptions!$C$6+(YEAR(B13)-YEAR(Assumptions!$C$4))*Assumptions!$C$7 -> 3000 | D13: =Assumptions!$D$23*(1+Assumptions!$F$23)^((B13-Assumptions!$C$4)/365) -> 186.57726 | E13: =C13/D13 -> 16.07913 | F13: =F12+E13 -> 151.71388 | G13: =F13*D13 -> 28306.36 | H13: =Assumptions!$D$24*(1+Assumptions!$F$24)^((B13-Assumptions!$C$4)/365) -> 162.78073 | I13: =C13/H13 -> 18.4297 | J13: =J12+I13 -> 173.48414 | K13: =J13*H13 -> 28239.876 | L13: =L12+C13 -> 27000
A14: 10 | B14: =EDATE(B13,1) -> 45931 | C14: =Assumptions!$C$6+(YEAR(B14)-YEAR(Assumptions!$C$4))*Assumptions!$C$7 -> 3000 | D14: =Assumptions!$D$23*(1+Assumptions!$F$23)^((B14-Assumptions!$C$4)/365) -> 188.73289 | E14: =C14/D14 -> 15.895481 | F14: =F13+E14 -> 167.60936 | G14: =F14*D14 -> 31633.398 | H14: =Assumptions!$D$24*(1+Assumptions!$F$24)^((B14-Assumptions!$C$4)/365) -> 164.56815 | I14: =C14/H14 -> 18.229529 | J14: =J13+I14 -> 191.71367 | K14: =J14*H14 -> 31549.965 | L14: =L13+C14 -> 30000
A15: 11 | B15: =EDATE(B14,1) -> 45962 | C15: =Assumptions!$C$6+(YEAR(B15)-YEAR(Assumptions!$C$4))*Assumptions!$C$7 -> 3000 | D15: =Assumptions!$D$23*(1+Assumptions!$F$23)^((B15-Assumptions!$C$4)/365) -> 190.98653 | E15: =C15/D15 -> 15.707914 | F15: =F14+E15 -> 183.31727 | G15: =F15*D15 -> 35011.13 | H15: =Assumptions!$D$24*(1+Assumptions!$F$24)^((B15-Assumptions!$C$4)/365) -> 166.43578 | I15: =C15/H15 -> 18.02497 | J15: =J14+I15 -> 209.73864 | K15: =J15*H15 -> 34908.015 | L15: =L14+C15 -> 33000
A16: 12 | B16: =EDATE(B15,1) -> 45992 | C16: =Assumptions!$C$6+(YEAR(B16)-YEAR(Assumptions!$C$4))*Assumptions!$C$7 -> 3000 | D16: =Assumptions!$D$23*(1+Assumptions!$F$23)^((B16-Assumptions!$C$4)/365) -> 193.1931 | E16: =C16/D16 -> 15.528505 | F16: =F15+E16 -> 198.84578 | G16: =F16*D16 -> 38415.631 | H16: =Assumptions!$D$24*(1+Assumptions!$F$24)^((B16-Assumptions!$C$4)/365) -> 168.26334 | I16: =C16/H16 -> 17.829196 | J16: =J15+I16 -> 227.56784 | K16: =J16*H16 -> 38291.325 | L16: =L15+C16 -> 36000
A17: 13 | B17: =EDATE(B16,1) -> 46023 | C17: =Assumptions!$C$6+(YEAR(B17)-YEAR(Assumptions!$C$4))*Assumptions!$C$7 -> 4000 | D17: =Assumptions!$D$23*(1+Assumptions!$F$23)^((B17-Assumptions!$C$4)/365) -> 195.5 | E17: =C17/D17 -> 20.460358 | F17: =F16+E17 -> 219.30614 | G17: =F17*D17 -> 42874.349 | H17: =Assumptions!$D$24*(1+Assumptions!$F$24)^((B17-Assumptions!$C$4)/365) -> 170.1729 | I17: =C17/H17 -> 23.505505 | J17: =J16+I17 -> 251.07335 | K17: =J17*H17 -> 42725.879 | L17: =L16+C17 -> 40000
... A124: 120 | B124: =EDATE(B123,1) -> 49279 | C124: =Assumptions!$C$6+(YEAR(B124)-YEAR(Assumptions!$C$4))*Assumptions!$C$7 -> 12000 | D124: =Assumptions!$D$23*(1+Assumptions!$F$23)^((B124-Assumptions!$C$4)/365) -> 680.15009 | E124: =C124/D124 -> 17.643165 | F124: =F123+E124 -> 2440.9893 | G124: =F124*D124 -> 1660239.1 | H124: =Assumptions!$D$24*(1+Assumptions!$F$24)^((B124-Assumptions!$C$4)/365) -> 556.72775 | I124: =C124/H124 -> 21.554521 | J124: =J123+I124 -> 2883.2951 | K124: =J124*H124 -> 1605210.4 | L124: =L123+C124 -> 900000
B126: 10-YEAR TOTALS → | G126: =G124 -> 1660239.1 | K126: =K124 -> 1605210.4 | L126: =L124 -> 900000

Sheet Withdrawal_Jan2036
A1: What Do You Actually Take Home on 15-Jan-2036?
A2: ~11 years in · all 120 SIP instalments (Jan-2025–Dec-2034) · each instalment is its own tax lot · click − on the left margin to collapse lot detail
A4: Parag Parikh Flexi Cap Fund
A5: Direct Plan — all 120 SIP instalments
A6: Lot (SIP Month) | B6: Purchase Date | C6: Invested (₹) | D6: NAV @ Purchase (₹) | E6: Units | F6: Holding Days | G6: NAV @ 15-Jan-2036 (₹) | H6: Gross Value (₹) | I6: Exit Load % | J6: Exit Load Amt (₹) | K6: Net Redemption (₹) | L6: Capital Gain (₹) | M6: Gain Type | N6: Tax Rate | O6: Tax Amt (₹)
A7: =TEXT(SIP_Fund1_PPFAS!B5,"mmm-yyyy") -> Jan-2025 | B7: =SIP_Fund1_PPFAS!B5 -> 45658 | C7: =SIP_Fund1_PPFAS!C5 -> 3000 | D7: =SIP_Fund1_PPFAS!D5 -> 75 | E7: =SIP_Fund1_PPFAS!E5 -> 40 | F7: =Assumptions!$C$5-B7 -> 4031 | G7: =Assumptions!$D$19*(1+Assumptions!$F$19)^((Assumptions!$C$5-Assumptions!$C$4)/365) -> 262.19054 | H7: =E7*G7 -> 10487.622 | I7: =IF(F7<365,Assumptions!$G$19,IF(F7<=730,Assumptions!$H$19,Assumptions!$I$19)) -> 0 | J7: =H7*I7 -> 0 | K7: =H7-J7 -> 10487.622 | L7: =K7-C7 -> 7487.6215 | M7: =IF(F7>365,"LTCG","STCG") -> LTCG | N7: =IF(M7="LTCG",Assumptions!$C$12,Assumptions!$C$11) -> 0.125 | O7: =IF(M7="STCG",MAX(L7,0)*Assumptions!$C$11,"agg. below") -> agg. below
A8: =TEXT(SIP_Fund1_PPFAS!B6,"mmm-yyyy") -> Feb-2025 | B8: =SIP_Fund1_PPFAS!B6 -> 45689 | C8: =SIP_Fund1_PPFAS!C6 -> 3000 | D8: =SIP_Fund1_PPFAS!D6 -> 75.725374 | E8: =SIP_Fund1_PPFAS!E6 -> 39.61684 | F8: =Assumptions!$C$5-B8 -> 4000 | G8: =Assumptions!$D$19*(1+Assumptions!$F$19)^((Assumptions!$C$5-Assumptions!$C$4)/365) -> 262.19054 | H8: =E8*G8 -> 10387.161 | I8: =IF(F8<365,Assumptions!$G$19,IF(F8<=730,Assumptions!$H$19,Assumptions!$I$19)) -> 0 | J8: =H8*I8 -> 0 | K8: =H8-J8 -> 10387.161 | L8: =K8-C8 -> 7387.1606 | M8: =IF(F8>365,"LTCG","STCG") -> LTCG | N8: =IF(M8="LTCG",Assumptions!$C$12,Assumptions!$C$11) -> 0.125 | O8: =IF(M8="STCG",MAX(L8,0)*Assumptions!$C$11,"agg. below") -> agg. below
A9: =TEXT(SIP_Fund1_PPFAS!B7,"mmm-yyyy") -> Mar-2025 | B9: =SIP_Fund1_PPFAS!B7 -> 45717 | C9: =SIP_Fund1_PPFAS!C7 -> 3000 | D9: =SIP_Fund1_PPFAS!D7 -> 76.386578 | E9: =SIP_Fund1_PPFAS!E7 -> 39.273915 | F9: =Assumptions!$C$5-B9 -> 3972 | G9: =Assumptions!$D$19*(1+Assumptions!$F$19)^((Assumptions!$C$5-Assumptions!$C$4)/365) -> 262.19054 | H9: =E9*G9 -> 10297.249 | I9: =IF(F9<365,Assumptions!$G$19,IF(F9<=730,Assumptions!$H$19,Assumptions!$I$19)) -> 0 | J9: =H9*I9 -> 0 | K9: =H9-J9 -> 10297.249 | L9: =K9-C9 -> 7297.249 | M9: =IF(F9>365,"LTCG","STCG") -> LTCG | N9: =IF(M9="LTCG",Assumptions!$C$12,Assumptions!$C$11) -> 0.125 | O9: =IF(M9="STCG",MAX(L9,0)*Assumptions!$C$11,"agg. below") -> agg. below
A10: =TEXT(SIP_Fund1_PPFAS!B8,"mmm-yyyy") -> Apr-2025 | B10: =SIP_Fund1_PPFAS!B8 -> 45748 | C10: =SIP_Fund1_PPFAS!C8 -> 3000 | D10: =SIP_Fund1_PPFAS!D8 -> 77.125362 | E10: =SIP_Fund1_PPFAS!E8 -> 38.897711 | F10: =Assumptions!$C$5-B10 -> 3941 | G10: =Assumptions!$D$19*(1+Assumptions!$F$19)^((Assumptions!$C$5-Assumptions!$C$4)/365) -> 262.19054 | H10: =E10*G10 -> 10198.612 | I10: =IF(F10<365,Assumptions!$G$19,IF(F10<=730,Assumptions!$H$19,Assumptions!$I$19)) -> 0 | J10: =H10*I10 -> 0 | K10: =H10-J10 -> 10198.612 | L10: =K10-C10 -> 7198.6117 | M10: =IF(F10>365,"LTCG","STCG") -> LTCG | N10: =IF(M10="LTCG",Assumptions!$C$12,Assumptions!$C$11) -> 0.125 | O10: =IF(M10="STCG",MAX(L10,0)*Assumptions!$C$11,"agg. below") -> agg. below
A11: =TEXT(SIP_Fund1_PPFAS!B9,"mmm-yyyy") -> May-2025 | B11: =SIP_Fund1_PPFAS!B9 -> 45778 | C11: =SIP_Fund1_PPFAS!C9 -> 3000 | D11: =SIP_Fund1_PPFAS!D9 -> 77.847117 | E11: =SIP_Fund1_PPFAS!E9 -> 38.537073 | F11: =Assumptions!$C$5-B11 -> 3911 | G11: =Assumptions!$D$19*(1+Assumptions!$F$19)^((Assumptions!$C$5-Assumptions!$C$4)/365) -> 262.19054 | H11: =E11*G11 -> 10104.056 | I11: =IF(F11<365,Assumptions!$G$19,IF(F11<=730,Assumptions!$H$19,Assumptions!$I$19)) -> 0 | J11: =H11*I11 -> 0 | K11: =H11-J11 -> 10104.056 | L11: =K11-C11 -> 7104.0559 | M11: =IF(F11>365,"LTCG","STCG") -> LTCG | N11: =IF(M11="LTCG",Assumptions!$C$12,Assumptions!$C$11) -> 0.125 | O11: =IF(M11="STCG",MAX(L11,0)*Assumptions!$C$11,"agg. below") -> agg. below
A12: =TEXT(SIP_Fund1_PPFAS!B10,"mmm-yyyy") -> Jun-2025 | B12: =SIP_Fund1_PPFAS!B10 -> 45809 | C12: =SIP_Fund1_PPFAS!C10 -> 3000 | D12: =SIP_Fund1_PPFAS!D10 -> 78.600026 | E12: =SIP_Fund1_PPFAS!E10 -> 38.167926 | F12: =Assumptions!$C$5-B12 -> 3880 | G12: =Assumptions!$D$19*(1+Assumptions!$F$19)^((Assumptions!$C$5-Assumptions!$C$4)/365) -> 262.19054 | H12: =E12*G12 -> 10007.269 | I12: =IF(F12<365,Assumptions!$G$19,IF(F12<=730,Assumptions!$H$19,Assumptions!$I$19)) -> 0 | J12: =H12*I12 -> 0 | K12: =H12-J12 -> 10007.269 | L12: =K12-C12 -> 7007.2691 | M12: =IF(F12>365,"LTCG","STCG") -> LTCG | N12: =IF(M12="LTCG",Assumptions!$C$12,Assumptions!$C$11) -> 0.125 | O12: =IF(M12="STCG",MAX(L12,0)*Assumptions!$C$11,"agg. below") -> agg. below
A13: =TEXT(SIP_Fund1_PPFAS!B11,"mmm-yyyy") -> Jul-2025 | B13: =SIP_Fund1_PPFAS!B11 -> 45839 | C13: =SIP_Fund1_PPFAS!C11 -> 3000 | D13: =SIP_Fund1_PPFAS!D11 -> 79.335581 | E13: =SIP_Fund1_PPFAS!E11 -> 37.814055 | F13: =Assumptions!$C$5-B13 -> 3850 | G13: =Assumptions!$D$19*(1+Assumptions!$F$19)^((Assumptions!$C$5-Assumptions!$C$4)/365) -> 262.19054 | H13: =E13*G13 -> 9914.4873 | I13: =IF(F13<365,Assumptions!$G$19,IF(F13<=730,Assumptions!$H$19,Assumptions!$I$19)) -> 0 | J13: =H13*I13 -> 0 | K13: =H13-J13 -> 9914.4873 | L13: =K13-C13 -> 6914.4873 | M13: =IF(F13>365,"LTCG","STCG") -> LTCG | N13: =IF(M13="LTCG",Assumptions!$C$12,Assumptions!$C$11) -> 0.125 | O13: =IF(M13="STCG",MAX(L13,0)*Assumptions!$C$11,"agg. below") -> agg. below
A14: =TEXT(SIP_Fund1_PPFAS!B12,"mmm-yyyy") -> Aug-2025 | B14: =SIP_Fund1_PPFAS!B12 -> 45870 | C14: =SIP_Fund1_PPFAS!C12 -> 3000 | D14: =SIP_Fund1_PPFAS!D12 -> 80.102887 | E14: =SIP_Fund1_PPFAS!E12 -> 37.451834 | F14: =Assumptions!$C$5-B14 -> 3819 | G14: =Assumptions!$D$19*(1+Assumptions!$F$19)^((Assumptions!$C$5-Assumptions!$C$4)/365) -> 262.19054 | H14: =E14*G14 -> 9819.5164 | I14: =IF(F14<365,Assumptions!$G$19,IF(F14<=730,Assumptions!$H$19,Assumptions!$I$19)) -> 0 | J14: =H14*I14 -> 0 | K14: =H14-J14 -> 9819.5164 | L14: =K14-C14 -> 6819.5164 | M14: =IF(F14>365,"LTCG","STCG") -> LTCG | N14: =IF(M14="LTCG",Assumptions!$C$12,Assumptions!$C$11) -> 0.125 | O14: =IF(M14="STCG",MAX(L14,0)*Assumptions!$C$11,"agg. below") -> agg. below
A15: =TEXT(SIP_Fund1_PPFAS!B13,"mmm-yyyy") -> Sep-2025 | B15: =SIP_Fund1_PPFAS!B13 -> 45901 | C15: =SIP_Fund1_PPFAS!C13 -> 3000 | D15: =SIP_Fund1_PPFAS!D13 -> 80.877614 | E15: =SIP_Fund1_PPFAS!E13 -> 37.093082 | F15: =Assumptions!$C$5-B15 -> 3788 | G15: =Assumptions!$D$19*(1+Assumptions!$F$19)^((Assumptions!$C$5-Assumptions!$C$4)/365) -> 262.19054 | H15: =E15*G15 -> 9725.4552 | I15: =IF(F15<365,Assumptions!$G$19,IF(F15<=730,Assumptions!$H$19,Assumptions!$I$19)) -> 0 | J15: =H15*I15 -> 0 | K15: =H15-J15 -> 9725.4552 | L15: =K15-C15 -> 6725.4552 | M15: =IF(F15>365,"LTCG","STCG") -> LTCG | N15: =IF(M15="LTCG",Assumptions!$C$12,Assumptions!$C$11) -> 0.125 | O15: =IF(M15="STCG",MAX(L15,0)*Assumptions!$C$11,"agg. below") -> agg. below
A16: =TEXT(SIP_Fund1_PPFAS!B14,"mmm-yyyy") -> Oct-2025 | B16: =SIP_Fund1_PPFAS!B14 -> 45931 | C16: =SIP_Fund1_PPFAS!C14 -> 3000 | D16: =SIP_Fund1_PPFAS!D14 -> 81.634483 | E16: =SIP_Fund1_PPFAS!E14 -> 36.749176 | F16: =Assumptions!$C$5-B16 -> 3758 | G16: =Assumptions!$D$19*(1+Assumptions!$F$19)^((Assumptions!$C$5-Assumptions!$C$4)/365) -> 262.19054 | H16: =E16*G16 -> 9635.2863 | I16: =IF(F16<365,Assumptions!$G$19,IF(F16<=730,Assumptions!$H$19,Assumptions!$I$19)) -> 0 | J16: =H16*I16 -> 0 | K16: =H16-J16 -> 9635.2863 | L16: =K16-C16 -> 6635.2863 | M16: =IF(F16>365,"LTCG","STCG") -> LTCG | N16: =IF(M16="LTCG",Assumptions!$C$12,Assumptions!$C$11) -> 0.125 | O16: =IF(M16="STCG",MAX(L16,0)*Assumptions!$C$11,"agg. below") -> agg. below
A17: =TEXT(SIP_Fund1_PPFAS!B15,"mmm-yyyy") -> Nov-2025 | B17: =SIP_Fund1_PPFAS!B15 -> 45962 | C17: =SIP_Fund1_PPFAS!C15 -> 3000 | D17: =SIP_Fund1_PPFAS!D15 -> 82.424023 | E17: =SIP_Fund1_PPFAS!E15 -> 36.397156 | F17: =Assumptions!$C$5-B17 -> 3727 | G17: =Assumptions!$D$19*(1+Assumptions!$F$19)^((Assumptions!$C$5-Assumptions!$C$4)/365) -> 262.19054 | H17: =E17*G17 -> 9542.9898 | I17: =IF(F17<365,Assumptions!$G$19,IF(F17<=730,Assumptions!$H$19,Assumptions!$I$19)) -> 0 | J17: =H17*I17 -> 0 | K17: =H17-J17 -> 9542.9898 | L17: =K17-C17 -> 6542.9898 | M17: =IF(F17>365,"LTCG","STCG") -> LTCG | N17: =IF(M17="LTCG",Assumptions!$C$12,Assumptions!$C$11) -> 0.125 | O17: =IF(M17="STCG",MAX(L17,0)*Assumptions!$C$11,"agg. below") -> agg. below
A18: =TEXT(SIP_Fund1_PPFAS!B16,"mmm-yyyy") -> Dec-2025 | B18: =SIP_Fund1_PPFAS!B16 -> 45992 | C18: =SIP_Fund1_PPFAS!C16 -> 3000 | D18: =SIP_Fund1_PPFAS!D16 -> 83.195364 | E18: =SIP_Fund1_PPFAS!E16 -> 36.059702 | F18: =Assumptions!$C$5-B18 -> 3697 | G18: =Assumptions!$D$19*(1+Assumptions!$F$19)^((Assumptions!$C$5-Assumptions!$C$4)/365) -> 262.19054 | H18: =E18*G18 -> 9454.5126 | I18: =IF(F18<365,Assumptions!$G$19,IF(F18<=730,Assumptions!$H$19,Assumptions!$I$19)) -> 0 | J18: =H18*I18 -> 0 | K18: =H18-J18 -> 9454.5126 | L18: =K18-C18 -> 6454.5126 | M18: =IF(F18>365,"LTCG","STCG") -> LTCG | N18: =IF(M18="LTCG",Assumptions!$C$12,Assumptions!$C$11) -> 0.125 | O18: =IF(M18="STCG",MAX(L18,0)*Assumptions!$C$11,"agg. below") -> agg. below
... A126: =TEXT(SIP_Fund1_PPFAS!B124,"mmm-yyyy") -> Dec-2034 | B126: =SIP_Fund1_PPFAS!B124 -> 49279 | C126: =SIP_Fund1_PPFAS!C124 -> 12000 | D126: =SIP_Fund1_PPFAS!D124 -> 230.8506 | E126: =SIP_Fund1_PPFAS!E124 -> 51.98167 | F126: =Assumptions!$C$5-B126 -> 410 | G126: =Assumptions!$D$19*(1+Assumptions!$F$19)^((Assumptions!$C$5-Assumptions!$C$4)/365) -> 262.19054 | H126: =E126*G126 -> 13629.102 | I126: =IF(F126<365,Assumptions!$G$19,IF(F126<=730,Assumptions!$H$19,Assumptions!$I$19)) -> 0.01 | J126: =H126*I126 -> 136.29102 | K126: =H126-J126 -> 13492.811 | L126: =K126-C126 -> 1492.8111 | M126: =IF(F126>365,"LTCG","STCG") -> LTCG | N126: =IF(M126="LTCG",Assumptions!$C$12,Assumptions!$C$11) -> 0.125 | O126: =IF(M126="STCG",MAX(L126,0)*Assumptions!$C$11,"agg. below") -> agg. below
A127: SUBTOTAL | C127: =SUM(C7:C126) -> 900000 | H127: =SUM(H7:H126) -> 1660328.7 | J127: =SUM(J7:J126) -> 1572.532 | K127: =SUM(K7:K126) -> 1658756.2 | L127: =SUM(L7:L126) -> 758756.16 | O127: =SUMIF(M7:M126,"STCG",O7:O126)+MAX(0,SUMIF(M7:M126,"LTCG",L7:L126)-Assumptions!$C$13)*Assumptions!$C$12 -> 79219.52
A128: NET AMOUNT RECEIVED (after exit load & tax) | O128: =K127-O127 -> 1579536.6
A130: Regular Plan — all 120 SIP instalments
A131: Lot (SIP Month) | B131: Purchase Date | C131: Invested (₹) | D131: NAV @ Purchase (₹) | E131: Units | F131: Holding Days | G131: NAV @ 15-Jan-2036 (₹) | H131: Gross Value (₹) | I131: Exit Load % | J131: Exit Load Amt (₹) | K131: Net Redemption (₹) | L131: Capital Gain (₹) | M131: Gain Type | N131: Tax Rate | O131: Tax Amt (₹)
A132: =TEXT(SIP_Fund1_PPFAS!B5,"mmm-yyyy") -> Jan-2025 | B132: =SIP_Fund1_PPFAS!B5 -> 45658 | C132: =SIP_Fund1_PPFAS!C5 -> 3000 | D132: =SIP_Fund1_PPFAS!H5 -> 70 | E132: =SIP_Fund1_PPFAS!I5 -> 42.857143 | F132: =Assumptions!$C$5-B132 -> 4031 | G132: =Assumptions!$D$20*(1+Assumptions!$F$20)^((Assumptions!$C$5-Assumptions!$C$4)/365) -> 232.45212 | H132: =E132*G132 -> 9962.2336 | I132: =IF(F132<365,Assumptions!$G$20,IF(F132<=730,Assumptions!$H$20,Assumptions!$I$20)) -> 0 | J132: =H132*I132 -> 0 | K132: =H132-J132 -> 9962.2336 | L132: =K132-C132 -> 6962.2336 | M132: =IF(F132>365,"LTCG","STCG") -> LTCG | N132: =IF(M132="LTCG",Assumptions!$C$12,Assumptions!$C$11) -> 0.125 | O132: =IF(M132="STCG",MAX(L132,0)*Assumptions!$C$11,"agg. below") -> agg. below
A133: =TEXT(SIP_Fund1_PPFAS!B6,"mmm-yyyy") -> Feb-2025 | B133: =SIP_Fund1_PPFAS!B6 -> 45689 | C133: =SIP_Fund1_PPFAS!C6 -> 3000 | D133: =SIP_Fund1_PPFAS!H6 -> 70.649086 | E133: =SIP_Fund1_PPFAS!I6 -> 42.463394 | F133: =Assumptions!$C$5-B133 -> 4000 | G133: =Assumptions!$D$20*(1+Assumptions!$F$20)^((Assumptions!$C$5-Assumptions!$C$4)/365) -> 232.45212 | H133: =E133*G133 -> 9870.7059 | I133: =IF(F133<365,Assumptions!$G$20,IF(F133<=730,Assumptions!$H$20,Assumptions!$I$20)) -> 0 | J133: =H133*I133 -> 0 | K133: =H133-J133 -> 9870.7059 | L133: =K133-C133 -> 6870.7059 | M133: =IF(F133>365,"LTCG","STCG") -> LTCG | N133: =IF(M133="LTCG",Assumptions!$C$12,Assumptions!$C$11) -> 0.125 | O133: =IF(M133="STCG",MAX(L133,0)*Assumptions!$C$11,"agg. below") -> agg. below
A134: =TEXT(SIP_Fund1_PPFAS!B7,"mmm-yyyy") -> Mar-2025 | B134: =SIP_Fund1_PPFAS!B7 -> 45717 | C134: =SIP_Fund1_PPFAS!C7 -> 3000 | D134: =SIP_Fund1_PPFAS!H7 -> 71.240529 | E134: =SIP_Fund1_PPFAS!I7 -> 42.110861 | F134: =Assumptions!$C$5-B134 -> 3972 | G134: =Assumptions!$D$20*(1+Assumptions!$F$20)^((Assumptions!$C$5-Assumptions!$C$4)/365) -> 232.45212 | H134: =E134*G134 -> 9788.7588 | I134: =IF(F134<365,Assumptions!$G$20,IF(F134<=730,Assumptions!$H$20,Assumptions!$I$20)) -> 0 | J134: =H134*I134 -> 0 | K134: =H134-J134 -> 9788.7588 | L134: =K134-C134 -> 6788.7588 | M134: =IF(F134>365,"LTCG","STCG") -> LTCG | N134: =IF(M134="LTCG",Assumptions!$C$12,Assumptions!$C$11) -> 0.125 | O134: =IF(M134="STCG",MAX(L134,0)*Assumptions!$C$11,"agg. below") -> agg. below
A135: =TEXT(SIP_Fund1_PPFAS!B8,"mmm-yyyy") -> Apr-2025 | B135: =SIP_Fund1_PPFAS!B8 -> 45748 | C135: =SIP_Fund1_PPFAS!C8 -> 3000 | D135: =SIP_Fund1_PPFAS!H8 -> 71.901119 | E135: =SIP_Fund1_PPFAS!I8 -> 41.723968 | F135: =Assumptions!$C$5-B135 -> 3941 | G135: =Assumptions!$D$20*(1+Assumptions!$F$20)^((Assumptions!$C$5-Assumptions!$C$4)/365) -> 232.45212 | H135: =E135*G135 -> 9698.8248 | I135: =IF(F135<365,Assumptions!$G$20,IF(F135<=730,Assumptions!$H$20,Assumptions!$I$20)) -> 0 | J135: =H135*I135 -> 0 | K135: =H135-J135 -> 9698.8248 | L135: =K135-C135 -> 6698.8248 | M135: =IF(F135>365,"LTCG","STCG") -> LTCG | N135: =IF(M135="LTCG",Assumptions!$C$12,Assumptions!$C$11) -> 0.125 | O135: =IF(M135="STCG",MAX(L135,0)*Assumptions!$C$11,"agg. below") -> agg. below
A136: =TEXT(SIP_Fund1_PPFAS!B9,"mmm-yyyy") -> May-2025 | B136: =SIP_Fund1_PPFAS!B9 -> 45778 | C136: =SIP_Fund1_PPFAS!C9 -> 3000 | D136: =SIP_Fund1_PPFAS!H9 -> 72.54623 | E136: =SIP_Fund1_PPFAS!I9 -> 41.352941 | F136: =Assumptions!$C$5-B136 -> 3911 | G136: =Assumptions!$D$20*(1+Assumptions!$F$20)^((Assumptions!$C$5-Assumptions!$C$4)/365) -> 232.45212 | H136: =E136*G136 -> 9612.5788 | I136: =IF(F136<365,Assumptions!$G$20,IF(F136<=730,Assumptions!$H$20,Assumptions!$I$20)) -> 0 | J136: =H136*I136 -> 0 | K136: =H136-J136 -> 9612.5788 | L136: =K136-C136 -> 6612.5788 | M136: =IF(F136>365,"LTCG","STCG") -> LTCG | N136: =IF(M136="LTCG",Assumptions!$C$12,Assumptions!$C$11) -> 0.125 | O136: =IF(M136="STCG",MAX(L136,0)*Assumptions!$C$11,"agg. below") -> agg. below
A137: =TEXT(SIP_Fund1_PPFAS!B10,"mmm-yyyy") -> Jun-2025 | B137: =SIP_Fund1_PPFAS!B10 -> 45809 | C137: =SIP_Fund1_PPFAS!C10 -> 3000 | D137: =SIP_Fund1_PPFAS!H10 -> 73.218927 | E137: =SIP_Fund1_PPFAS!I10 -> 40.973013 | F137: =Assumptions!$C$5-B137 -> 3880 | G137: =Assumptions!$D$20*(1+Assumptions!$F$20)^((Assumptions!$C$5-Assumptions!$C$4)/365) -> 232.45212 | H137: =E137*G137 -> 9524.2636 | I137: =IF(F137<365,Assumptions!$G$20,IF(F137<=730,Assumptions!$H$20,Assumptions!$I$20)) -> 0 | J137: =H137*I137 -> 0 | K137: =H137-J137 -> 9524.2636 | L137: =K137-C137 -> 6524.2636 | M137: =IF(F137>365,"LTCG","STCG") -> LTCG | N137: =IF(M137="LTCG",Assumptions!$C$12,Assumptions!$C$11) -> 0.125 | O137: =IF(M137="STCG",MAX(L137,0)*Assumptions!$C$11,"agg. below") -> agg. below
A138: =TEXT(SIP_Fund1_PPFAS!B11,"mmm-yyyy") -> Jul-2025 | B138: =SIP_Fund1_PPFAS!B11 -> 45839 | C138: =SIP_Fund1_PPFAS!C11 -> 3000 | D138: =SIP_Fund1_PPFAS!H11 -> 73.875862 | E138: =SIP_Fund1_PPFAS!I11 -> 40.608663 | F138: =Assumptions!$C$5-B138 -> 3850 | G138: =Assumptions!$D$20*(1+Assumptions!$F$20)^((Assumptions!$C$5-Assumptions!$C$4)/365) -> 232.45212 | H138: =E138*G138 -> 9439.5698 | I138: =IF(F138<365,Assumptions!$G$20,IF(F138<=730,Assumptions!$H$20,Assumptions!$I$20)) -> 0 | J138: =H138*I138 -> 0 | K138: =H138-J138 -> 9439.5698 | L138: =K138-C138 -> 6439.5698 | M138: =IF(F138>365,"LTCG","STCG") -> LTCG | N138: =IF(M138="LTCG",Assumptions!$C$12,Assumptions!$C$11) -> 0.125 | O138: =IF(M138="STCG",MAX(L138,0)*Assumptions!$C$11,"agg. below") -> agg. below
A139: =TEXT(SIP_Fund1_PPFAS!B12,"mmm-yyyy") -> Aug-2025 | B139: =SIP_Fund1_PPFAS!B12 -> 45870 | C139: =SIP_Fund1_PPFAS!C12 -> 3000 | D139: =SIP_Fund1_PPFAS!H12 -> 74.560888 | E139: =SIP_Fund1_PPFAS!I12 -> 40.235573 | F139: =Assumptions!$C$5-B139 -> 3819 | G139: =Assumptions!$D$20*(1+Assumptions!$F$20)^((Assumptions!$C$5-Assumptions!$C$4)/365) -> 232.45212 | H139: =E139*G139 -> 9352.8441 | I139: =IF(F139<365,Assumptions!$G$20,IF(F139<=730,Assumptions!$H$20,Assumptions!$I$20)) -> 0 | J139: =H139*I139 -> 0 | K139: =H139-J139 -> 9352.8441 | L139: =K139-C139 -> 6352.8441 | M139: =IF(F139>365,"LTCG","STCG") -> LTCG | N139: =IF(M139="LTCG",Assumptions!$C$12,Assumptions!$C$11) -> 0.125 | O139: =IF(M139="STCG",MAX(L139,0)*Assumptions!$C$11,"agg. below") -> agg. below
A140: =TEXT(SIP_Fund1_PPFAS!B13,"mmm-yyyy") -> Sep-2025 | B140: =SIP_Fund1_PPFAS!B13 -> 45901 | C140: =SIP_Fund1_PPFAS!C13 -> 3000 | D140: =SIP_Fund1_PPFAS!H13 -> 75.252265 | E140: =SIP_Fund1_PPFAS!I13 -> 39.86591 | F140: =Assumptions!$C$5-B140 -> 3788 | G140: =Assumptions!$D$20*(1+Assumptions!$F$20)^((Assumptions!$C$5-Assumptions!$C$4)/365) -> 232.45212 | H140: =E140*G140 -> 9266.9151 | I140: =IF(F140<365,Assumptions!$G$20,IF(F140<=730,Assumptions!$H$20,Assumptions!$I$20)) -> 0 | J140: =H140*I140 -> 0 | K140: =H140-J140 -> 9266.9151 | L140: =K140-C140 -> 6266.9151 | M140: =IF(F140>365,"LTCG","STCG") -> LTCG | N140: =IF(M140="LTCG",Assumptions!$C$12,Assumptions!$C$11) -> 0.125 | O140: =IF(M140="STCG",MAX(L140,0)*Assumptions!$C$11,"agg. below") -> agg. below
A141: =TEXT(SIP_Fund1_PPFAS!B14,"mmm-yyyy") -> Oct-2025 | B141: =SIP_Fund1_PPFAS!B14 -> 45931 | C141: =SIP_Fund1_PPFAS!C14 -> 3000 | D141: =SIP_Fund1_PPFAS!H14 -> 75.927444 | E141: =SIP_Fund1_PPFAS!I14 -> 39.511405 | F141: =Assumptions!$C$5-B141 -> 3758 | G141: =Assumptions!$D$20*(1+Assumptions!$F$20)^((Assumptions!$C$5-Assumptions!$C$4)/365) -> 232.45212 | H141: =E141*G141 -> 9184.5098 | I141: =IF(F141<365,Assumptions!$G$20,IF(F141<=730,Assumptions!$H$20,Assumptions!$I$20)) -> 0 | J141: =H141*I141 -> 0 | K141: =H141-J141 -> 9184.5098 | L141: =K141-C141 -> 6184.5098 | M141: =IF(F141>365,"LTCG","STCG") -> LTCG | N141: =IF(M141="LTCG",Assumptions!$C$12,Assumptions!$C$11) -> 0.125 | O141: =IF(M141="STCG",MAX(L141,0)*Assumptions!$C$11,"agg. below") -> agg. below
A142: =TEXT(SIP_Fund1_PPFAS!B15,"mmm-yyyy") -> Nov-2025 | B142: =SIP_Fund1_PPFAS!B15 -> 45962 | C142: =SIP_Fund1_PPFAS!C15 -> 3000 | D142: =SIP_Fund1_PPFAS!H15 -> 76.631493 | E142: =SIP_Fund1_PPFAS!I15 -> 39.148395 | F142: =Assumptions!$C$5-B142 -> 3727 | G142: =Assumptions!$D$20*(1+Assumptions!$F$20)^((Assumptions!$C$5-Assumptions!$C$4)/365) -> 232.45212 | H142: =E142*G142 -> 9100.1274 | I142: =IF(F142<365,Assumptions!$G$20,IF(F142<=730,Assumptions!$H$20,Assumptions!$I$20)) -> 0 | J142: =H142*I142 -> 0 | K142: =H142-J142 -> 9100.1274 | L142: =K142-C142 -> 6100.1274 | M142: =IF(F142>365,"LTCG","STCG") -> LTCG | N142: =IF(M142="LTCG",Assumptions!$C$12,Assumptions!$C$11) -> 0.125 | O142: =IF(M142="STCG",MAX(L142,0)*Assumptions!$C$11,"agg. below") -> agg. below
A143: =TEXT(SIP_Fund1_PPFAS!B16,"mmm-yyyy") -> Dec-2025 | B143: =SIP_Fund1_PPFAS!B16 -> 45992 | C143: =SIP_Fund1_PPFAS!C16 -> 3000 | D143: =SIP_Fund1_PPFAS!H16 -> 77.319047 | E143: =SIP_Fund1_PPFAS!I16 -> 38.800271 | F143: =Assumptions!$C$5-B143 -> 3697 | G143: =Assumptions!$D$20*(1+Assumptions!$F$20)^((Assumptions!$C$5-Assumptions!$C$4)/365) -> 232.45212 | H143: =E143*G143 -> 9019.2053 | I143: =IF(F143<365,Assumptions!$G$20,IF(F143<=730,Assumptions!$H$20,Assumptions!$I$20)) -> 0 | J143: =H143*I143 -> 0 | K143: =H143-J143 -> 9019.2053 | L143: =K143-C143 -> 6019.2053 | M143: =IF(F143>365,"LTCG","STCG") -> LTCG | N143: =IF(M143="LTCG",Assumptions!$C$12,Assumptions!$C$11) -> 0.125 | O143: =IF(M143="STCG",MAX(L143,0)*Assumptions!$C$11,"agg. below") -> agg. below
... A251: =TEXT(SIP_Fund1_PPFAS!B124,"mmm-yyyy") -> Dec-2034 | B251: =SIP_Fund1_PPFAS!B124 -> 49279 | C251: =SIP_Fund1_PPFAS!C124 -> 12000 | D251: =SIP_Fund1_PPFAS!H124 -> 205.73953 | E251: =SIP_Fund1_PPFAS!I124 -> 58.326176 | F251: =Assumptions!$C$5-B251 -> 410 | G251: =Assumptions!$D$20*(1+Assumptions!$F$20)^((Assumptions!$C$5-Assumptions!$C$4)/365) -> 232.45212 | H251: =E251*G251 -> 13558.043 | I251: =IF(F251<365,Assumptions!$G$20,IF(F251<=730,Assumptions!$H$20,Assumptions!$I$20)) -> 0.01 | J251: =H251*I251 -> 135.58043 | K251: =H251-J251 -> 13422.463 | L251: =K251-C251 -> 1422.4626 | M251: =IF(F251>365,"LTCG","STCG") -> LTCG | N251: =IF(M251="LTCG",Assumptions!$C$12,Assumptions!$C$11) -> 0.125 | O251: =IF(M251="STCG",MAX(L251,0)*Assumptions!$C$11,"agg. below") -> agg. below
A252: SUBTOTAL | C252: =SUM(C132:C251) -> 900000 | H252: =SUM(H132:H251) -> 1615989.2 | J252: =SUM(J132:J251) -> 1561.241 | K252: =SUM(K132:K251) -> 1614428 | L252: =SUM(L132:L251) -> 714428.01 | O252: =SUMIF(M132:M251,"STCG",O132:O251)+MAX(0,SUMIF(M132:M251,"LTCG",L132:L251)-Assumptions!$C$13)*Assumptions!$C$12 -> 73678.501
A253: NET AMOUNT RECEIVED (after exit load & tax) | O253: =K252-O252 -> 1540749.5
A255: Cost of choosing Regular over Direct for Parag Parikh Flexi Cap Fund (full SIP + ~11-year holding period) | O255: =O128-O253 -> 38787.135
A258: HDFC Mid-Cap Opportunities Fund
A259: Direct Plan — all 120 SIP instalments
A260: Lot (SIP Month) | B260: Purchase Date | C260: Invested (₹) | D260: NAV @ Purchase (₹) | E260: Units | F260: Holding Days | G260: NAV @ 15-Jan-2036 (₹) | H260: Gross Value (₹) | I260: Exit Load % | J260: Exit Load Amt (₹) | K260: Net Redemption (₹) | L260: Capital Gain (₹) | M260: Gain Type | N260: Tax Rate | O260: Tax Amt (₹)
A261: =TEXT(SIP_Fund2_HDFCMidcap!B5,"mmm-yyyy") -> Jan-2025 | B261: =SIP_Fund2_HDFCMidcap!B5 -> 45658 | C261: =SIP_Fund2_HDFCMidcap!C5 -> 3000 | D261: =SIP_Fund2_HDFCMidcap!D5 -> 190 | E261: =SIP_Fund2_HDFCMidcap!E5 -> 15.789474 | F261: =Assumptions!$C$5-B261 -> 4031 | G261: =Assumptions!$D$21*(1+Assumptions!$F$21)^((Assumptions!$C$5-Assumptions!$C$4)/365) -> 807.60951 | H261: =E261*G261 -> 12751.729 | I261: =IF(F261<365,Assumptions!$G$21,IF(F261<=730,Assumptions!$H$21,Assumptions!$I$21)) -> 0 | J261: =H261*I261 -> 0 | K261: =H261-J261 -> 12751.729 | L261: =K261-C261 -> 9751.7291 | M261: =IF(F261>365,"LTCG","STCG") -> LTCG | N261: =IF(M261="LTCG",Assumptions!$C$12,Assumptions!$C$11) -> 0.125 | O261: =IF(M261="STCG",MAX(L261,0)*Assumptions!$C$11,"agg. below") -> agg. below
A262: =TEXT(SIP_Fund2_HDFCMidcap!B6,"mmm-yyyy") -> Feb-2025 | B262: =SIP_Fund2_HDFCMidcap!B6 -> 45689 | C262: =SIP_Fund2_HDFCMidcap!C6 -> 3000 | D262: =SIP_Fund2_HDFCMidcap!D6 -> 192.12621 | E262: =SIP_Fund2_HDFCMidcap!E6 -> 15.614736 | F262: =Assumptions!$C$5-B262 -> 4000 | G262: =Assumptions!$D$21*(1+Assumptions!$F$21)^((Assumptions!$C$5-Assumptions!$C$4)/365) -> 807.60951 | H262: =E262*G262 -> 12610.609 | I262: =IF(F262<365,Assumptions!$G$21,IF(F262<=730,Assumptions!$H$21,Assumptions!$I$21)) -> 0 | J262: =H262*I262 -> 0 | K262: =H262-J262 -> 12610.609 | L262: =K262-C262 -> 9610.6091 | M262: =IF(F262>365,"LTCG","STCG") -> LTCG | N262: =IF(M262="LTCG",Assumptions!$C$12,Assumptions!$C$11) -> 0.125 | O262: =IF(M262="STCG",MAX(L262,0)*Assumptions!$C$11,"agg. below") -> agg. below
A263: =TEXT(SIP_Fund2_HDFCMidcap!B7,"mmm-yyyy") -> Mar-2025 | B263: =SIP_Fund2_HDFCMidcap!B7 -> 45717 | C263: =SIP_Fund2_HDFCMidcap!C7 -> 3000 | D263: =SIP_Fund2_HDFCMidcap!D7 -> 194.0671 | E263: =SIP_Fund2_HDFCMidcap!E7 -> 15.458571 | F263: =Assumptions!$C$5-B263 -> 3972 | G263: =Assumptions!$D$21*(1+Assumptions!$F$21)^((Assumptions!$C$5-Assumptions!$C$4)/365) -> 807.60951 | H263: =E263*G263 -> 12484.489 | I263: =IF(F263<365,Assumptions!$G$21,IF(F263<=730,Assumptions!$H$21,Assumptions!$I$21)) -> 0 | J263: =H263*I263 -> 0 | K263: =H263-J263 -> 12484.489 | L263: =K263-C263 -> 9484.4887 | M263: =IF(F263>365,"LTCG","STCG") -> LTCG | N263: =IF(M263="LTCG",Assumptions!$C$12,Assumptions!$C$11) -> 0.125 | O263: =IF(M263="STCG",MAX(L263,0)*Assumptions!$C$11,"agg. below") -> agg. below
A264: =TEXT(SIP_Fund2_HDFCMidcap!B8,"mmm-yyyy") -> Apr-2025 | B264: =SIP_Fund2_HDFCMidcap!B8 -> 45748 | C264: =SIP_Fund2_HDFCMidcap!C8 -> 3000 | D264: =SIP_Fund2_HDFCMidcap!D8 -> 196.23882 | E264: =SIP_Fund2_HDFCMidcap!E8 -> 15.287495 | F264: =Assumptions!$C$5-B264 -> 3941 | G264: =Assumptions!$D$21*(1+Assumptions!$F$21)^((Assumptions!$C$5-Assumptions!$C$4)/365) -> 807.60951 | H264: =E264*G264 -> 12346.326 | I264: =IF(F264<365,Assumptions!$G$21,IF(F264<=730,Assumptions!$H$21,Assumptions!$I$21)) -> 0 | J264: =H264*I264 -> 0 | K264: =H264-J264 -> 12346.326 | L264: =K264-C264 -> 9346.3262 | M264: =IF(F264>365,"LTCG","STCG") -> LTCG | N264: =IF(M264="LTCG",Assumptions!$C$12,Assumptions!$C$11) -> 0.125 | O264: =IF(M264="STCG",MAX(L264,0)*Assumptions!$C$11,"agg. below") -> agg. below
A265: =TEXT(SIP_Fund2_HDFCMidcap!B9,"mmm-yyyy") -> May-2025 | B265: =SIP_Fund2_HDFCMidcap!B9 -> 45778 | C265: =SIP_Fund2_HDFCMidcap!C9 -> 3000 | D265: =SIP_Fund2_HDFCMidcap!D9 -> 198.36363 | E265: =SIP_Fund2_HDFCMidcap!E9 -> 15.12374 | F265: =Assumptions!$C$5-B265 -> 3911 | G265: =Assumptions!$D$21*(1+Assumptions!$F$21)^((Assumptions!$C$5-Assumptions!$C$4)/365) -> 807.60951 | H265: =E265*G265 -> 12214.076 | I265: =IF(F265<365,Assumptions!$G$21,IF(F265<=730,Assumptions!$H$21,Assumptions!$I$21)) -> 0 | J265: =H265*I265 -> 0 | K265: =H265-J265 -> 12214.076 | L265: =K265-C265 -> 9214.0765 | M265: =IF(F265>365,"LTCG","STCG") -> LTCG | N265: =IF(M265="LTCG",Assumptions!$C$12,Assumptions!$C$11) -> 0.125 | O265: =IF(M265="STCG",MAX(L265,0)*Assumptions!$C$11,"agg. below") -> agg. below
A266: =TEXT(SIP_Fund2_HDFCMidcap!B10,"mmm-yyyy") -> Jun-2025 | B266: =SIP_Fund2_HDFCMidcap!B10 -> 45809 | C266: =SIP_Fund2_HDFCMidcap!C10 -> 3000 | D266: =SIP_Fund2_HDFCMidcap!D10 -> 200.58343 | E266: =SIP_Fund2_HDFCMidcap!E10 -> 14.95637 | F266: =Assumptions!$C$5-B266 -> 3880 | G266: =Assumptions!$D$21*(1+Assumptions!$F$21)^((Assumptions!$C$5-Assumptions!$C$4)/365) -> 807.60951 | H266: =E266*G266 -> 12078.907 | I266: =IF(F266<365,Assumptions!$G$21,IF(F266<=730,Assumptions!$H$21,Assumptions!$I$21)) -> 0 | J266: =H266*I266 -> 0 | K266: =H266-J266 -> 12078.907 | L266: =K266-C266 -> 9078.9065 | M266: =IF(F266>365,"LTCG","STCG") -> LTCG | N266: =IF(M266="LTCG",Assumptions!$C$12,Assumptions!$C$11) -> 0.125 | O266: =IF(M266="STCG",MAX(L266,0)*Assumptions!$C$11,"agg. below") -> agg. below
A267: =TEXT(SIP_Fund2_HDFCMidcap!B11,"mmm-yyyy") -> Jul-2025 | B267: =SIP_Fund2_HDFCMidcap!B11 -> 45839 | C267: =SIP_Fund2_HDFCMidcap!C11 -> 3000 | D267: =SIP_Fund2_HDFCMidcap!D11 -> 202.75528 | E267: =SIP_Fund2_HDFCMidcap!E11 -> 14.796162 | F267: =Assumptions!$C$5-B267 -> 3850 | G267: =Assumptions!$D$21*(1+Assumptions!$F$21)^((Assumptions!$C$5-Assumptions!$C$4)/365) -> 807.60951 | H267: =E267*G267 -> 11949.521 | I267: =IF(F267<365,Assumptions!$G$21,IF(F267<=730,Assumptions!$H$21,Assumptions!$I$21)) -> 0 | J267: =H267*I267 -> 0 | K267: =H267-J267 -> 11949.521 | L267: =K267-C267 -> 8949.5213 | M267: =IF(F267>365,"LTCG","STCG") -> LTCG | N267: =IF(M267="LTCG",Assumptions!$C$12,Assumptions!$C$11) -> 0.125 | O267: =IF(M267="STCG",MAX(L267,0)*Assumptions!$C$11,"agg. below") -> agg. below
A268: =TEXT(SIP_Fund2_HDFCMidcap!B12,"mmm-yyyy") -> Aug-2025 | B268: =SIP_Fund2_HDFCMidcap!B12 -> 45870 | C268: =SIP_Fund2_HDFCMidcap!C12 -> 3000 | D268: =SIP_Fund2_HDFCMidcap!D12 -> 205.02423 | E268: =SIP_Fund2_HDFCMidcap!E12 -> 14.632417 | F268: =Assumptions!$C$5-B268 -> 3819 | G268: =Assumptions!$D$21*(1+Assumptions!$F$21)^((Assumptions!$C$5-Assumptions!$C$4)/365) -> 807.60951 | H268: =E268*G268 -> 11817.279 | I268: =IF(F268<365,Assumptions!$G$21,IF(F268<=730,Assumptions!$H$21,Assumptions!$I$21)) -> 0 | J268: =H268*I268 -> 0 | K268: =H268-J268 -> 11817.279 | L268: =K268-C268 -> 8817.2791 | M268: =IF(F268>365,"LTCG","STCG") -> LTCG | N268: =IF(M268="LTCG",Assumptions!$C$12,Assumptions!$C$11) -> 0.125 | O268: =IF(M268="STCG",MAX(L268,0)*Assumptions!$C$11,"agg. below") -> agg. below
A269: =TEXT(SIP_Fund2_HDFCMidcap!B13,"mmm-yyyy") -> Sep-2025 | B269: =SIP_Fund2_HDFCMidcap!B13 -> 45901 | C269: =SIP_Fund2_HDFCMidcap!C13 -> 3000 | D269: =SIP_Fund2_HDFCMidcap!D13 -> 207.31857 | E269: =SIP_Fund2_HDFCMidcap!E13 -> 14.470484 | F269: =Assumptions!$C$5-B269 -> 3788 | G269: =Assumptions!$D$21*(1+Assumptions!$F$21)^((Assumptions!$C$5-Assumptions!$C$4)/365) -> 807.60951 | H269: =E269*G269 -> 11686.5 | I269: =IF(F269<365,Assumptions!$G$21,IF(F269<=730,Assumptions!$H$21,Assumptions!$I$21)) -> 0 | J269: =H269*I269 -> 0 | K269: =H269-J269 -> 11686.5 | L269: =K269-C269 -> 8686.5004 | M269: =IF(F269>365,"LTCG","STCG") -> LTCG | N269: =IF(M269="LTCG",Assumptions!$C$12,Assumptions!$C$11) -> 0.125 | O269: =IF(M269="STCG",MAX(L269,0)*Assumptions!$C$11,"agg. below") -> agg. below
A270: =TEXT(SIP_Fund2_HDFCMidcap!B14,"mmm-yyyy") -> Oct-2025 | B270: =SIP_Fund2_HDFCMidcap!B14 -> 45931 | C270: =SIP_Fund2_HDFCMidcap!C14 -> 3000 | D270: =SIP_Fund2_HDFCMidcap!D14 -> 209.56334 | E270: =SIP_Fund2_HDFCMidcap!E14 -> 14.315481 | F270: =Assumptions!$C$5-B270 -> 3758 | G270: =Assumptions!$D$21*(1+Assumptions!$F$21)^((Assumptions!$C$5-Assumptions!$C$4)/365) -> 807.60951 | H270: =E270*G270 -> 11561.319 | I270: =IF(F270<365,Assumptions!$G$21,IF(F270<=730,Assumptions!$H$21,Assumptions!$I$21)) -> 0 | J270: =H270*I270 -> 0 | K270: =H270-J270 -> 11561.319 | L270: =K270-C270 -> 8561.3186 | M270: =IF(F270>365,"LTCG","STCG") -> LTCG | N270: =IF(M270="LTCG",Assumptions!$C$12,Assumptions!$C$11) -> 0.125 | O270: =IF(M270="STCG",MAX(L270,0)*Assumptions!$C$11,"agg. below") -> agg. below
A271: =TEXT(SIP_Fund2_HDFCMidcap!B15,"mmm-yyyy") -> Nov-2025 | B271: =SIP_Fund2_HDFCMidcap!B15 -> 45962 | C271: =SIP_Fund2_HDFCMidcap!C15 -> 3000 | D271: =SIP_Fund2_HDFCMidcap!D15 -> 211.90848 | E271: =SIP_Fund2_HDFCMidcap!E15 -> 14.157055 | F271: =Assumptions!$C$5-B271 -> 3727 | G271: =Assumptions!$D$21*(1+Assumptions!$F$21)^((Assumptions!$C$5-Assumptions!$C$4)/365) -> 807.60951 | H271: =E271*G271 -> 11433.373 | I271: =IF(F271<365,Assumptions!$G$21,IF(F271<=730,Assumptions!$H$21,Assumptions!$I$21)) -> 0 | J271: =H271*I271 -> 0 | K271: =H271-J271 -> 11433.373 | L271: =K271-C271 -> 8433.3725 | M271: =IF(F271>365,"LTCG","STCG") -> LTCG | N271: =IF(M271="LTCG",Assumptions!$C$12,Assumptions!$C$11) -> 0.125 | O271: =IF(M271="STCG",MAX(L271,0)*Assumptions!$C$11,"agg. below") -> agg. below
A272: =TEXT(SIP_Fund2_HDFCMidcap!B16,"mmm-yyyy") -> Dec-2025 | B272: =SIP_Fund2_HDFCMidcap!B16 -> 45992 | C272: =SIP_Fund2_HDFCMidcap!C16 -> 3000 | D272: =SIP_Fund2_HDFCMidcap!D16 -> 214.20295 | E272: =SIP_Fund2_HDFCMidcap!E16 -> 14.00541 | F272: =Assumptions!$C$5-B272 -> 3697 | G272: =Assumptions!$D$21*(1+Assumptions!$F$21)^((Assumptions!$C$5-Assumptions!$C$4)/365) -> 807.60951 | H272: =E272*G272 -> 11310.902 | I272: =IF(F272<365,Assumptions!$G$21,IF(F272<=730,Assumptions!$H$21,Assumptions!$I$21)) -> 0 | J272: =H272*I272 -> 0 | K272: =H272-J272 -> 11310.902 | L272: =K272-C272 -> 8310.9021 | M272: =IF(F272>365,"LTCG","STCG") -> LTCG | N272: =IF(M272="LTCG",Assumptions!$C$12,Assumptions!$C$11) -> 0.125 | O272: =IF(M272="STCG",MAX(L272,0)*Assumptions!$C$11,"agg. below") -> agg. below
... A380: =TEXT(SIP_Fund2_HDFCMidcap!B124,"mmm-yyyy") -> Dec-2034 | B380: =SIP_Fund2_HDFCMidcap!B124 -> 49279 | C380: =SIP_Fund2_HDFCMidcap!C124 -> 12000 | D380: =SIP_Fund2_HDFCMidcap!D124 -> 697.07725 | E380: =SIP_Fund2_HDFCMidcap!E124 -> 17.214735 | F380: =Assumptions!$C$5-B380 -> 410 | G380: =Assumptions!$D$21*(1+Assumptions!$F$21)^((Assumptions!$C$5-Assumptions!$C$4)/365) -> 807.60951 | H380: =E380*G380 -> 13902.784 | I380: =IF(F380<365,Assumptions!$G$21,IF(F380<=730,Assumptions!$H$21,Assumptions!$I$21)) -> 0 | J380: =H380*I380 -> 0 | K380: =H380-J380 -> 13902.784 | L380: =K380-C380 -> 1902.7836 | M380: =IF(F380>365,"LTCG","STCG") -> LTCG | N380: =IF(M380="LTCG",Assumptions!$C$12,Assumptions!$C$11) -> 0.125 | O380: =IF(M380="STCG",MAX(L380,0)*Assumptions!$C$11,"agg. below") -> agg. below
A381: SUBTOTAL | C381: =SUM(C261:C380) -> 900000 | H381: =SUM(H261:H380) -> 1843195 | J381: =SUM(J261:J380) -> 0 | K381: =SUM(K261:K380) -> 1843195 | L381: =SUM(L261:L380) -> 943195.04 | O381: =SUMIF(M261:M380,"STCG",O261:O380)+MAX(0,SUMIF(M261:M380,"LTCG",L261:L380)-Assumptions!$C$13)*Assumptions!$C$12 -> 102274.38
A382: NET AMOUNT RECEIVED (after exit load & tax) | O382: =K381-O381 -> 1740920.7
A384: Regular Plan — all 120 SIP instalments
A385: Lot (SIP Month) | B385: Purchase Date | C385: Invested (₹) | D385: NAV @ Purchase (₹) | E385: Units | F385: Holding Days | G385: NAV @ 15-Jan-2036 (₹) | H385: Gross Value (₹) | I385: Exit Load % | J385: Exit Load Amt (₹) | K385: Net Redemption (₹) | L385: Capital Gain (₹) | M385: Gain Type | N385: Tax Rate | O385: Tax Amt (₹)
A386: =TEXT(SIP_Fund2_HDFCMidcap!B5,"mmm-yyyy") -> Jan-2025 | B386: =SIP_Fund2_HDFCMidcap!B5 -> 45658 | C386: =SIP_Fund2_HDFCMidcap!C5 -> 3000 | D386: =SIP_Fund2_HDFCMidcap!H5 -> 168 | E386: =SIP_Fund2_HDFCMidcap!I5 -> 17.857143 | F386: =Assumptions!$C$5-B386 -> 4031 | G386: =Assumptions!$D$22*(1+Assumptions!$F$22)^((Assumptions!$C$5-Assumptions!$C$4)/365) -> 681.58437 | H386: =E386*G386 -> 12171.149 | I386: =IF(F386<365,Assumptions!$G$22,IF(F386<=730,Assumptions!$H$22,Assumptions!$I$22)) -> 0 | J386: =H386*I386 -> 0 | K386: =H386-J386 -> 12171.149 | L386: =K386-C386 -> 9171.1494 | M386: =IF(F386>365,"LTCG","STCG") -> LTCG | N386: =IF(M386="LTCG",Assumptions!$C$12,Assumptions!$C$11) -> 0.125 | O386: =IF(M386="STCG",MAX(L386,0)*Assumptions!$C$11,"agg. below") -> agg. below
A387: =TEXT(SIP_Fund2_HDFCMidcap!B6,"mmm-yyyy") -> Feb-2025 | B387: =SIP_Fund2_HDFCMidcap!B6 -> 45689 | C387: =SIP_Fund2_HDFCMidcap!C6 -> 3000 | D387: =SIP_Fund2_HDFCMidcap!H6 -> 169.81915 | E387: =SIP_Fund2_HDFCMidcap!I6 -> 17.665852 | F387: =Assumptions!$C$5-B387 -> 4000 | G387: =Assumptions!$D$22*(1+Assumptions!$F$22)^((Assumptions!$C$5-Assumptions!$C$4)/365) -> 681.58437 | H387: =E387*G387 -> 12040.769 | I387: =IF(F387<365,Assumptions!$G$22,IF(F387<=730,Assumptions!$H$22,Assumptions!$I$22)) -> 0 | J387: =H387*I387 -> 0 | K387: =H387-J387 -> 12040.769 | L387: =K387-C387 -> 9040.7687 | M387: =IF(F387>365,"LTCG","STCG") -> LTCG | N387: =IF(M387="LTCG",Assumptions!$C$12,Assumptions!$C$11) -> 0.125 | O387: =IF(M387="STCG",MAX(L387,0)*Assumptions!$C$11,"agg. below") -> agg. below
A388: =TEXT(SIP_Fund2_HDFCMidcap!B7,"mmm-yyyy") -> Mar-2025 | B388: =SIP_Fund2_HDFCMidcap!B7 -> 45717 | C388: =SIP_Fund2_HDFCMidcap!C7 -> 3000 | D388: =SIP_Fund2_HDFCMidcap!H7 -> 171.47918 | E388: =SIP_Fund2_HDFCMidcap!I7 -> 17.494835 | F388: =Assumptions!$C$5-B388 -> 3972 | G388: =Assumptions!$D$22*(1+Assumptions!$F$22)^((Assumptions!$C$5-Assumptions!$C$4)/365) -> 681.58437 | H388: =E388*G388 -> 11924.206 | I388: =IF(F388<365,Assumptions!$G$22,IF(F388<=730,Assumptions!$H$22,Assumptions!$I$22)) -> 0 | J388: =H388*I388 -> 0 | K388: =H388-J388 -> 11924.206 | L388: =K388-C388 -> 8924.2063 | M388: =IF(F388>365,"LTCG","STCG") -> LTCG | N388: =IF(M388="LTCG",Assumptions!$C$12,Assumptions!$C$11) -> 0.125 | O388: =IF(M388="STCG",MAX(L388,0)*Assumptions!$C$11,"agg. below") -> agg. below
A389: =TEXT(SIP_Fund2_HDFCMidcap!B8,"mmm-yyyy") -> Apr-2025 | B389: =SIP_Fund2_HDFCMidcap!B8 -> 45748 | C389: =SIP_Fund2_HDFCMidcap!C8 -> 3000 | D389: =SIP_Fund2_HDFCMidcap!H8 -> 173.336 | E389: =SIP_Fund2_HDFCMidcap!I8 -> 17.307426 | F389: =Assumptions!$C$5-B389 -> 3941 | G389: =Assumptions!$D$22*(1+Assumptions!$F$22)^((Assumptions!$C$5-Assumptions!$C$4)/365) -> 681.58437 | H389: =E389*G389 -> 11796.471 | I389: =IF(F389<365,Assumptions!$G$22,IF(F389<=730,Assumptions!$H$22,Assumptions!$I$22)) -> 0 | J389: =H389*I389 -> 0 | K389: =H389-J389 -> 11796.471 | L389: =K389-C389 -> 8796.4709 | M389: =IF(F389>365,"LTCG","STCG") -> LTCG | N389: =IF(M389="LTCG",Assumptions!$C$12,Assumptions!$C$11) -> 0.125 | O389: =IF(M389="STCG",MAX(L389,0)*Assumptions!$C$11,"agg. below") -> agg. below
A390: =TEXT(SIP_Fund2_HDFCMidcap!B9,"mmm-yyyy") -> May-2025 | B390: =SIP_Fund2_HDFCMidcap!B9 -> 45778 | C390: =SIP_Fund2_HDFCMidcap!C9 -> 3000 | D390: =SIP_Fund2_HDFCMidcap!H9 -> 175.15207 | E390: =SIP_Fund2_HDFCMidcap!I9 -> 17.127974 | F390: =Assumptions!$C$5-B390 -> 3911 | G390: =Assumptions!$D$22*(1+Assumptions!$F$22)^((Assumptions!$C$5-Assumptions!$C$4)/365) -> 681.58437 | H390: =E390*G390 -> 11674.159 | I390: =IF(F390<365,Assumptions!$G$22,IF(F390<=730,Assumptions!$H$22,Assumptions!$I$22)) -> 0 | J390: =H390*I390 -> 0 | K390: =H390-J390 -> 11674.159 | L390: =K390-C390 -> 8674.159 | M390: =IF(F390>365,"LTCG","STCG") -> LTCG | N390: =IF(M390="LTCG",Assumptions!$C$12,Assumptions!$C$11) -> 0.125 | O390: =IF(M390="STCG",MAX(L390,0)*Assumptions!$C$11,"agg. below") -> agg. below
A391: =TEXT(SIP_Fund2_HDFCMidcap!B10,"mmm-yyyy") -> Jun-2025 | B391: =SIP_Fund2_HDFCMidcap!B10 -> 45809 | C391: =SIP_Fund2_HDFCMidcap!C10 -> 3000 | D391: =SIP_Fund2_HDFCMidcap!H10 -> 177.04866 | E391: =SIP_Fund2_HDFCMidcap!I10 -> 16.944494 | F391: =Assumptions!$C$5-B391 -> 3880 | G391: =Assumptions!$D$22*(1+Assumptions!$F$22)^((Assumptions!$C$5-Assumptions!$C$4)/365) -> 681.58437 | H391: =E391*G391 -> 11549.102 | I391: =IF(F391<365,Assumptions!$G$22,IF(F391<=730,Assumptions!$H$22,Assumptions!$I$22)) -> 0 | J391: =H391*I391 -> 0 | K391: =H391-J391 -> 11549.102 | L391: =K391-C391 -> 8549.1022 | M391: =IF(F391>365,"LTCG","STCG") -> LTCG | N391: =IF(M391="LTCG",Assumptions!$C$12,Assumptions!$C$11) -> 0.125 | O391: =IF(M391="STCG",MAX(L391,0)*Assumptions!$C$11,"agg. below") -> agg. below
A392: =TEXT(SIP_Fund2_HDFCMidcap!B11,"mmm-yyyy") -> Jul-2025 | B392: =SIP_Fund2_HDFCMidcap!B11 -> 45839 | C392: =SIP_Fund2_HDFCMidcap!C11 -> 3000 | D392: =SIP_Fund2_HDFCMidcap!H11 -> 178.90363 | E392: =SIP_Fund2_HDFCMidcap!I11 -> 16.768805 | F392: =Assumptions!$C$5-B392 -> 3850 | G392: =Assumptions!$D$22*(1+Assumptions!$F$22)^((Assumptions!$C$5-Assumptions!$C$4)/365) -> 681.58437 | H392: =E392*G392 -> 11429.355 | I392: =IF(F392<365,Assumptions!$G$22,IF(F392<=730,Assumptions!$H$22,Assumptions!$I$22)) -> 0 | J392: =H392*I392 -> 0 | K392: =H392-J392 -> 11429.355 | L392: =K392-C392 -> 8429.3551 | M392: =IF(F392>365,"LTCG","STCG") -> LTCG | N392: =IF(M392="LTCG",Assumptions!$C$12,Assumptions!$C$11) -> 0.125 | O392: =IF(M392="STCG",MAX(L392,0)*Assumptions!$C$11,"agg. below") -> agg. below
A393: =TEXT(SIP_Fund2_HDFCMidcap!B12,"mmm-yyyy") -> Aug-2025 | B393: =SIP_Fund2_HDFCMidcap!B12 -> 45870 | C393: =SIP_Fund2_HDFCMidcap!C12 -> 3000 | D393: =SIP_Fund2_HDFCMidcap!H12 -> 180.84085 | E393: =SIP_Fund2_HDFCMidcap!I12 -> 16.589173 | F393: =Assumptions!$C$5-B393 -> 3819 | G393: =Assumptions!$D$22*(1+Assumptions!$F$22)^((Assumptions!$C$5-Assumptions!$C$4)/365) -> 681.58437 | H393: =E393*G393 -> 11306.921 | I393: =IF(F393<365,Assumptions!$G$22,IF(F393<=730,Assumptions!$H$22,Assumptions!$I$22)) -> 0 | J393: =H393*I393 -> 0 | K393: =H393-J393 -> 11306.921 | L393: =K393-C393 -> 8306.9207 | M393: =IF(F393>365,"LTCG","STCG") -> LTCG | N393: =IF(M393="LTCG",Assumptions!$C$12,Assumptions!$C$11) -> 0.125 | O393: =IF(M393="STCG",MAX(L393,0)*Assumptions!$C$11,"agg. below") -> agg. below
A394: =TEXT(SIP_Fund2_HDFCMidcap!B13,"mmm-yyyy") -> Sep-2025 | B394: =SIP_Fund2_HDFCMidcap!B13 -> 45901 | C394: =SIP_Fund2_HDFCMidcap!C13 -> 3000 | D394: =SIP_Fund2_HDFCMidcap!H13 -> 182.79904 | E394: =SIP_Fund2_HDFCMidcap!I13 -> 16.411465 | F394: =Assumptions!$C$5-B394 -> 3788 | G394: =Assumptions!$D$22*(1+Assumptions!$F$22)^((Assumptions!$C$5-Assumptions!$C$4)/365) -> 681.58437 | H394: =E394*G394 -> 11185.798 | I394: =IF(F394<365,Assumptions!$G$22,IF(F394<=730,Assumptions!$H$22,Assumptions!$I$22)) -> 0 | J394: =H394*I394 -> 0 | K394: =H394-J394 -> 11185.798 | L394: =K394-C394 -> 8185.7978 | M394: =IF(F394>365,"LTCG","STCG") -> LTCG | N394: =IF(M394="LTCG",Assumptions!$C$12,Assumptions!$C$11) -> 0.125 | O394: =IF(M394="STCG",MAX(L394,0)*Assumptions!$C$11,"agg. below") -> agg. below
A395: =TEXT(SIP_Fund2_HDFCMidcap!B14,"mmm-yyyy") -> Oct-2025 | B395: =SIP_Fund2_HDFCMidcap!B14 -> 45931 | C395: =SIP_Fund2_HDFCMidcap!C14 -> 3000 | D395: =SIP_Fund2_HDFCMidcap!H14 -> 184.71425 | E395: =SIP_Fund2_HDFCMidcap!I14 -> 16.241302 | F395: =Assumptions!$C$5-B395 -> 3758 | G395: =Assumptions!$D$22*(1+Assumptions!$F$22)^((Assumptions!$C$5-Assumptions!$C$4)/365) -> 681.58437 | H395: =E395*G395 -> 11069.818 | I395: =IF(F395<365,Assumptions!$G$22,IF(F395<=730,Assumptions!$H$22,Assumptions!$I$22)) -> 0 | J395: =H395*I395 -> 0 | K395: =H395-J395 -> 11069.818 | L395: =K395-C395 -> 8069.8177 | M395: =IF(F395>365,"LTCG","STCG") -> LTCG | N395: =IF(M395="LTCG",Assumptions!$C$12,Assumptions!$C$11) -> 0.125 | O395: =IF(M395="STCG",MAX(L395,0)*Assumptions!$C$11,"agg. below") -> agg. below
A396: =TEXT(SIP_Fund2_HDFCMidcap!B15,"mmm-yyyy") -> Nov-2025 | B396: =SIP_Fund2_HDFCMidcap!B15 -> 45962 | C396: =SIP_Fund2_HDFCMidcap!C15 -> 3000 | D396: =SIP_Fund2_HDFCMidcap!H15 -> 186.71439 | E396: =SIP_Fund2_HDFCMidcap!I15 -> 16.067321 | F396: =Assumptions!$C$5-B396 -> 3727 | G396: =Assumptions!$D$22*(1+Assumptions!$F$22)^((Assumptions!$C$5-Assumptions!$C$4)/365) -> 681.58437 | H396: =E396*G396 -> 10951.235 | I396: =IF(F396<365,Assumptions!$G$22,IF(F396<=730,Assumptions!$H$22,Assumptions!$I$22)) -> 0 | J396: =H396*I396 -> 0 | K396: =H396-J396 -> 10951.235 | L396: =K396-C396 -> 7951.2348 | M396: =IF(F396>365,"LTCG","STCG") -> LTCG | N396: =IF(M396="LTCG",Assumptions!$C$12,Assumptions!$C$11) -> 0.125 | O396: =IF(M396="STCG",MAX(L396,0)*Assumptions!$C$11,"agg. below") -> agg. below
A397: =TEXT(SIP_Fund2_HDFCMidcap!B16,"mmm-yyyy") -> Dec-2025 | B397: =SIP_Fund2_HDFCMidcap!B16 -> 45992 | C397: =SIP_Fund2_HDFCMidcap!C16 -> 3000 | D397: =SIP_Fund2_HDFCMidcap!H16 -> 188.67062 | E397: =SIP_Fund2_HDFCMidcap!I16 -> 15.900727 | F397: =Assumptions!$C$5-B397 -> 3697 | G397: =Assumptions!$D$22*(1+Assumptions!$F$22)^((Assumptions!$C$5-Assumptions!$C$4)/365) -> 681.58437 | H397: =E397*G397 -> 10837.687 | I397: =IF(F397<365,Assumptions!$G$22,IF(F397<=730,Assumptions!$H$22,Assumptions!$I$22)) -> 0 | J397: =H397*I397 -> 0 | K397: =H397-J397 -> 10837.687 | L397: =K397-C397 -> 7837.6867 | M397: =IF(F397>365,"LTCG","STCG") -> LTCG | N397: =IF(M397="LTCG",Assumptions!$C$12,Assumptions!$C$11) -> 0.125 | O397: =IF(M397="STCG",MAX(L397,0)*Assumptions!$C$11,"agg. below") -> agg. below
... A505: =TEXT(SIP_Fund2_HDFCMidcap!B124,"mmm-yyyy") -> Dec-2034 | B505: =SIP_Fund2_HDFCMidcap!B124 -> 49279 | C505: =SIP_Fund2_HDFCMidcap!C124 -> 12000 | D505: =SIP_Fund2_HDFCMidcap!H124 -> 591.09528 | E505: =SIP_Fund2_HDFCMidcap!I124 -> 20.301296 | F505: =Assumptions!$C$5-B505 -> 410 | G505: =Assumptions!$D$22*(1+Assumptions!$F$22)^((Assumptions!$C$5-Assumptions!$C$4)/365) -> 681.58437 | H505: =E505*G505 -> 13837.046 | I505: =IF(F505<365,Assumptions!$G$22,IF(F505<=730,Assumptions!$H$22,Assumptions!$I$22)) -> 0 | J505: =H505*I505 -> 0 | K505: =H505-J505 -> 13837.046 | L505: =K505-C505 -> 1837.0457 | M505: =IF(F505>365,"LTCG","STCG") -> LTCG | N505: =IF(M505="LTCG",Assumptions!$C$12,Assumptions!$C$11) -> 0.125 | O505: =IF(M505="STCG",MAX(L505,0)*Assumptions!$C$11,"agg. below") -> agg. below
A506: SUBTOTAL | C506: =SUM(C386:C505) -> 900000 | H506: =SUM(H386:H505) -> 1797454.3 | J506: =SUM(J386:J505) -> 0 | K506: =SUM(K386:K505) -> 1797454.3 | L506: =SUM(L386:L505) -> 897454.33 | O506: =SUMIF(M386:M505,"STCG",O386:O505)+MAX(0,SUMIF(M386:M505,"LTCG",L386:L505)-Assumptions!$C$13)*Assumptions!$C$12 -> 96556.791
A507: NET AMOUNT RECEIVED (after exit load & tax) | O507: =K506-O506 -> 1700897.5
A509: Cost of choosing Regular over Direct for HDFC Mid-Cap Opportunities Fund (full SIP + ~11-year holding period) | O509: =O382-O507 -> 40023.121
A512: SBI Small Cap Fund
A513: Direct Plan — all 120 SIP instalments
A514: Lot (SIP Month) | B514: Purchase Date | C514: Invested (₹) | D514: NAV @ Purchase (₹) | E514: Units | F514: Holding Days | G514: NAV @ 15-Jan-2036 (₹) | H514: Gross Value (₹) | I514: Exit Load % | J514: Exit Load Amt (₹) | K514: Net Redemption (₹) | L514: Capital Gain (₹) | M514: Gain Type | N514: Tax Rate | O514: Tax Amt (₹)
A515: =TEXT(SIP_Fund3_SBISmallcap!B5,"mmm-yyyy") -> Jan-2025 | B515: =SIP_Fund3_SBISmallcap!B5 -> 45658 | C515: =SIP_Fund3_SBISmallcap!C5 -> 3000 | D515: =SIP_Fund3_SBISmallcap!D5 -> 170 | E515: =SIP_Fund3_SBISmallcap!E5 -> 17.647059 | F515: =Assumptions!$C$5-B515 -> 4031 | G515: =Assumptions!$D$23*(1+Assumptions!$F$23)^((Assumptions!$C$5-Assumptions!$C$4)/365) -> 795.76694 | H515: =E515*G515 -> 14042.946 | I515: =IF(F515<365,Assumptions!$G$23,IF(F515<=730,Assumptions!$H$23,Assumptions!$I$23)) -> 0 | J515: =H515*I515 -> 0 | K515: =H515-J515 -> 14042.946 | L515: =K515-C515 -> 11042.946 | M515: =IF(F515>365,"LTCG","STCG") -> LTCG | N515: =IF(M515="LTCG",Assumptions!$C$12,Assumptions!$C$11) -> 0.125 | O515: =IF(M515="STCG",MAX(L515,0)*Assumptions!$C$11,"agg. below") -> agg. below
A516: =TEXT(SIP_Fund3_SBISmallcap!B6,"mmm-yyyy") -> Feb-2025 | B516: =SIP_Fund3_SBISmallcap!B6 -> 45689 | C516: =SIP_Fund3_SBISmallcap!C6 -> 3000 | D516: =SIP_Fund3_SBISmallcap!D6 -> 172.02996 | E516: =SIP_Fund3_SBISmallcap!E6 -> 17.438823 | F516: =Assumptions!$C$5-B516 -> 4000 | G516: =Assumptions!$D$23*(1+Assumptions!$F$23)^((Assumptions!$C$5-Assumptions!$C$4)/365) -> 795.76694 | H516: =E516*G516 -> 13877.239 | I516: =IF(F516<365,Assumptions!$G$23,IF(F516<=730,Assumptions!$H$23,Assumptions!$I$23)) -> 0 | J516: =H516*I516 -> 0 | K516: =H516-J516 -> 13877.239 | L516: =K516-C516 -> 10877.239 | M516: =IF(F516>365,"LTCG","STCG") -> LTCG | N516: =IF(M516="LTCG",Assumptions!$C$12,Assumptions!$C$11) -> 0.125 | O516: =IF(M516="STCG",MAX(L516,0)*Assumptions!$C$11,"agg. below") -> agg. below
A517: =TEXT(SIP_Fund3_SBISmallcap!B7,"mmm-yyyy") -> Mar-2025 | B517: =SIP_Fund3_SBISmallcap!B7 -> 45717 | C517: =SIP_Fund3_SBISmallcap!C7 -> 3000 | D517: =SIP_Fund3_SBISmallcap!D7 -> 173.88429 | E517: =SIP_Fund3_SBISmallcap!E7 -> 17.252852 | F517: =Assumptions!$C$5-B517 -> 3972 | G517: =Assumptions!$D$23*(1+Assumptions!$F$23)^((Assumptions!$C$5-Assumptions!$C$4)/365) -> 795.76694 | H517: =E517*G517 -> 13729.249 | I517: =IF(F517<365,Assumptions!$G$23,IF(F517<=730,Assumptions!$H$23,Assumptions!$I$23)) -> 0 | J517: =H517*I517 -> 0 | K517: =H517-J517 -> 13729.249 | L517: =K517-C517 -> 10729.249 | M517: =IF(F517>365,"LTCG","STCG") -> LTCG | N517: =IF(M517="LTCG",Assumptions!$C$12,Assumptions!$C$11) -> 0.125 | O517: =IF(M517="STCG",MAX(L517,0)*Assumptions!$C$11,"agg. below") -> agg. below
A518: =TEXT(SIP_Fund3_SBISmallcap!B8,"mmm-yyyy") -> Apr-2025 | B518: =SIP_Fund3_SBISmallcap!B8 -> 45748 | C518: =SIP_Fund3_SBISmallcap!C8 -> 3000 | D518: =SIP_Fund3_SBISmallcap!D8 -> 175.96063 | E518: =SIP_Fund3_SBISmallcap!E8 -> 17.049268 | F518: =Assumptions!$C$5-B518 -> 3941 | G518: =Assumptions!$D$23*(1+Assumptions!$F$23)^((Assumptions!$C$5-Assumptions!$C$4)/365) -> 795.76694 | H518: =E518*G518 -> 13567.244 | I518: =IF(F518<365,Assumptions!$G$23,IF(F518<=730,Assumptions!$H$23,Assumptions!$I$23)) -> 0 | J518: =H518*I518 -> 0 | K518: =H518-J518 -> 13567.244 | L518: =K518-C518 -> 10567.244 | M518: =IF(F518>365,"LTCG","STCG") -> LTCG | N518: =IF(M518="LTCG",Assumptions!$C$12,Assumptions!$C$11) -> 0.125 | O518: =IF(M518="STCG",MAX(L518,0)*Assumptions!$C$11,"agg. below") -> agg. below
A519: =TEXT(SIP_Fund3_SBISmallcap!B9,"mmm-yyyy") -> May-2025 | B519: =SIP_Fund3_SBISmallcap!B9 -> 45778 | C519: =SIP_Fund3_SBISmallcap!C9 -> 3000 | D519: =SIP_Fund3_SBISmallcap!D9 -> 177.9936 | E519: =SIP_Fund3_SBISmallcap!E9 -> 16.854539 | F519: =Assumptions!$C$5-B519 -> 3911 | G519: =Assumptions!$D$23*(1+Assumptions!$F$23)^((Assumptions!$C$5-Assumptions!$C$4)/365) -> 795.76694 | H519: =E519*G519 -> 13412.285 | I519: =IF(F519<365,Assumptions!$G$23,IF(F519<=730,Assumptions!$H$23,Assumptions!$I$23)) -> 0 | J519: =H519*I519 -> 0 | K519: =H519-J519 -> 13412.285 | L519: =K519-C519 -> 10412.285 | M519: =IF(F519>365,"LTCG","STCG") -> LTCG | N519: =IF(M519="LTCG",Assumptions!$C$12,Assumptions!$C$11) -> 0.125 | O519: =IF(M519="STCG",MAX(L519,0)*Assumptions!$C$11,"agg. below") -> agg. below
A520: =TEXT(SIP_Fund3_SBISmallcap!B10,"mmm-yyyy") -> Jun-2025 | B520: =SIP_Fund3_SBISmallcap!B10 -> 45809 | C520: =SIP_Fund3_SBISmallcap!C10 -> 3000 | D520: =SIP_Fund3_SBISmallcap!D10 -> 180.119 | E520: =SIP_Fund3_SBISmallcap!E10 -> 16.655655 | F520: =Assumptions!$C$5-B520 -> 3880 | G520: =Assumptions!$D$23*(1+Assumptions!$F$23)^((Assumptions!$C$5-Assumptions!$C$4)/365) -> 795.76694 | H520: =E520*G520 -> 13254.02 | I520: =IF(F520<365,Assumptions!$G$23,IF(F520<=730,Assumptions!$H$23,Assumptions!$I$23)) -> 0 | J520: =H520*I520 -> 0 | K520: =H520-J520 -> 13254.02 | L520: =K520-C520 -> 10254.02 | M520: =IF(F520>365,"LTCG","STCG") -> LTCG | N520: =IF(M520="LTCG",Assumptions!$C$12,Assumptions!$C$11) -> 0.125 | O520: =IF(M520="STCG",MAX(L520,0)*Assumptions!$C$11,"agg. below") -> agg. below
A521: =TEXT(SIP_Fund3_SBISmallcap!B11,"mmm-yyyy") -> Jul-2025 | B521: =SIP_Fund3_SBISmallcap!B11 -> 45839 | C521: =SIP_Fund3_SBISmallcap!C11 -> 3000 | D521: =SIP_Fund3_SBISmallcap!D11 -> 182.20001 | E521: =SIP_Fund3_SBISmallcap!E11 -> 16.465422 | F521: =Assumptions!$C$5-B521 -> 3850 | G521: =Assumptions!$D$23*(1+Assumptions!$F$23)^((Assumptions!$C$5-Assumptions!$C$4)/365) -> 795.76694 | H521: =E521*G521 -> 13102.638 | I521: =IF(F521<365,Assumptions!$G$23,IF(F521<=730,Assumptions!$H$23,Assumptions!$I$23)) -> 0 | J521: =H521*I521 -> 0 | K521: =H521-J521 -> 13102.638 | L521: =K521-C521 -> 10102.638 | M521: =IF(F521>365,"LTCG","STCG") -> LTCG | N521: =IF(M521="LTCG",Assumptions!$C$12,Assumptions!$C$11) -> 0.125 | O521: =IF(M521="STCG",MAX(L521,0)*Assumptions!$C$11,"agg. below") -> agg. below
A522: =TEXT(SIP_Fund3_SBISmallcap!B12,"mmm-yyyy") -> Aug-2025 | B522: =SIP_Fund3_SBISmallcap!B12 -> 45870 | C522: =SIP_Fund3_SBISmallcap!C12 -> 3000 | D522: =SIP_Fund3_SBISmallcap!D12 -> 184.37565 | E522: =SIP_Fund3_SBISmallcap!E12 -> 16.271129 | F522: =Assumptions!$C$5-B522 -> 3819 | G522: =Assumptions!$D$23*(1+Assumptions!$F$23)^((Assumptions!$C$5-Assumptions!$C$4)/365) -> 795.76694 | H522: =E522*G522 -> 12948.027 | I522: =IF(F522<365,Assumptions!$G$23,IF(F522<=730,Assumptions!$H$23,Assumptions!$I$23)) -> 0 | J522: =H522*I522 -> 0 | K522: =H522-J522 -> 12948.027 | L522: =K522-C522 -> 9948.0268 | M522: =IF(F522>365,"LTCG","STCG") -> LTCG | N522: =IF(M522="LTCG",Assumptions!$C$12,Assumptions!$C$11) -> 0.125 | O522: =IF(M522="STCG",MAX(L522,0)*Assumptions!$C$11,"agg. below") -> agg. below
A523: =TEXT(SIP_Fund3_SBISmallcap!B13,"mmm-yyyy") -> Sep-2025 | B523: =SIP_Fund3_SBISmallcap!B13 -> 45901 | C523: =SIP_Fund3_SBISmallcap!C13 -> 3000 | D523: =SIP_Fund3_SBISmallcap!D13 -> 186.57726 | E523: =SIP_Fund3_SBISmallcap!E13 -> 16.07913 | F523: =Assumptions!$C$5-B523 -> 3788 | G523: =Assumptions!$D$23*(1+Assumptions!$F$23)^((Assumptions!$C$5-Assumptions!$C$4)/365) -> 795.76694 | H523: =E523*G523 -> 12795.24 | I523: =IF(F523<365,Assumptions!$G$23,IF(F523<=730,Assumptions!$H$23,Assumptions!$I$23)) -> 0 | J523: =H523*I523 -> 0 | K523: =H523-J523 -> 12795.24 | L523: =K523-C523 -> 9795.2398 | M523: =IF(F523>365,"LTCG","STCG") -> LTCG | N523: =IF(M523="LTCG",Assumptions!$C$12,Assumptions!$C$11) -> 0.125 | O523: =IF(M523="STCG",MAX(L523,0)*Assumptions!$C$11,"agg. below") -> agg. below
A524: =TEXT(SIP_Fund3_SBISmallcap!B14,"mmm-yyyy") -> Oct-2025 | B524: =SIP_Fund3_SBISmallcap!B14 -> 45931 | C524: =SIP_Fund3_SBISmallcap!C14 -> 3000 | D524: =SIP_Fund3_SBISmallcap!D14 -> 188.73289 | E524: =SIP_Fund3_SBISmallcap!E14 -> 15.895481 | F524: =Assumptions!$C$5-B524 -> 3758 | G524: =Assumptions!$D$23*(1+Assumptions!$F$23)^((Assumptions!$C$5-Assumptions!$C$4)/365) -> 795.76694 | H524: =E524*G524 -> 12649.098 | I524: =IF(F524<365,Assumptions!$G$23,IF(F524<=730,Assumptions!$H$23,Assumptions!$I$23)) -> 0 | J524: =H524*I524 -> 0 | K524: =H524-J524 -> 12649.098 | L524: =K524-C524 -> 9649.0983 | M524: =IF(F524>365,"LTCG","STCG") -> LTCG | N524: =IF(M524="LTCG",Assumptions!$C$12,Assumptions!$C$11) -> 0.125 | O524: =IF(M524="STCG",MAX(L524,0)*Assumptions!$C$11,"agg. below") -> agg. below
A525: =TEXT(SIP_Fund3_SBISmallcap!B15,"mmm-yyyy") -> Nov-2025 | B525: =SIP_Fund3_SBISmallcap!B15 -> 45962 | C525: =SIP_Fund3_SBISmallcap!C15 -> 3000 | D525: =SIP_Fund3_SBISmallcap!D15 -> 190.98653 | E525: =SIP_Fund3_SBISmallcap!E15 -> 15.707914 | F525: =Assumptions!$C$5-B525 -> 3727 | G525: =Assumptions!$D$23*(1+Assumptions!$F$23)^((Assumptions!$C$5-Assumptions!$C$4)/365) -> 795.76694 | H525: =E525*G525 -> 12499.839 | I525: =IF(F525<365,Assumptions!$G$23,IF(F525<=730,Assumptions!$H$23,Assumptions!$I$23)) -> 0 | J525: =H525*I525 -> 0 | K525: =H525-J525 -> 12499.839 | L525: =K525-C525 -> 9499.8387 | M525: =IF(F525>365,"LTCG","STCG") -> LTCG | N525: =IF(M525="LTCG",Assumptions!$C$12,Assumptions!$C$11) -> 0.125 | O525: =IF(M525="STCG",MAX(L525,0)*Assumptions!$C$11,"agg. below") -> agg. below
A526: =TEXT(SIP_Fund3_SBISmallcap!B16,"mmm-yyyy") -> Dec-2025 | B526: =SIP_Fund3_SBISmallcap!B16 -> 45992 | C526: =SIP_Fund3_SBISmallcap!C16 -> 3000 | D526: =SIP_Fund3_SBISmallcap!D16 -> 193.1931 | E526: =SIP_Fund3_SBISmallcap!E16 -> 15.528505 | F526: =Assumptions!$C$5-B526 -> 3697 | G526: =Assumptions!$D$23*(1+Assumptions!$F$23)^((Assumptions!$C$5-Assumptions!$C$4)/365) -> 795.76694 | H526: =E526*G526 -> 12357.071 | I526: =IF(F526<365,Assumptions!$G$23,IF(F526<=730,Assumptions!$H$23,Assumptions!$I$23)) -> 0 | J526: =H526*I526 -> 0 | K526: =H526-J526 -> 12357.071 | L526: =K526-C526 -> 9357.0711 | M526: =IF(F526>365,"LTCG","STCG") -> LTCG | N526: =IF(M526="LTCG",Assumptions!$C$12,Assumptions!$C$11) -> 0.125 | O526: =IF(M526="STCG",MAX(L526,0)*Assumptions!$C$11,"agg. below") -> agg. below
... A634: =TEXT(SIP_Fund3_SBISmallcap!B124,"mmm-yyyy") -> Dec-2034 | B634: =SIP_Fund3_SBISmallcap!B124 -> 49279 | C634: =SIP_Fund3_SBISmallcap!C124 -> 12000 | D634: =SIP_Fund3_SBISmallcap!D124 -> 680.15009 | E634: =SIP_Fund3_SBISmallcap!E124 -> 17.643165 | F634: =Assumptions!$C$5-B634 -> 410 | G634: =Assumptions!$D$23*(1+Assumptions!$F$23)^((Assumptions!$C$5-Assumptions!$C$4)/365) -> 795.76694 | H634: =E634*G634 -> 14039.847 | I634: =IF(F634<365,Assumptions!$G$23,IF(F634<=730,Assumptions!$H$23,Assumptions!$I$23)) -> 0 | J634: =H634*I634 -> 0 | K634: =H634-J634 -> 14039.847 | L634: =K634-C634 -> 2039.8472 | M634: =IF(F634>365,"LTCG","STCG") -> LTCG | N634: =IF(M634="LTCG",Assumptions!$C$12,Assumptions!$C$11) -> 0.125 | O634: =IF(M634="STCG",MAX(L634,0)*Assumptions!$C$11,"agg. below") -> agg. below
A635: SUBTOTAL | C635: =SUM(C515:C634) -> 900000 | H635: =SUM(H515:H634) -> 1942458.6 | J635: =SUM(J515:J634) -> 0 | K635: =SUM(K515:K634) -> 1942458.6 | L635: =SUM(L515:L634) -> 1042458.6 | O635: =SUMIF(M515:M634,"STCG",O515:O634)+MAX(0,SUMIF(M515:M634,"LTCG",L515:L634)-Assumptions!$C$13)*Assumptions!$C$12 -> 114682.32
A636: NET AMOUNT RECEIVED (after exit load & tax) | O636: =K635-O635 -> 1827776.2
A638: Regular Plan — all 120 SIP instalments
A639: Lot (SIP Month) | B639: Purchase Date | C639: Invested (₹) | D639: NAV @ Purchase (₹) | E639: Units | F639: Holding Days | G639: NAV @ 15-Jan-2036 (₹) | H639: Gross Value (₹) | I639: Exit Load % | J639: Exit Load Amt (₹) | K639: Net Redemption (₹) | L639: Capital Gain (₹) | M639: Gain Type | N639: Tax Rate | O639: Tax Amt (₹)
A640: =TEXT(SIP_Fund3_SBISmallcap!B5,"mmm-yyyy") -> Jan-2025 | B640: =SIP_Fund3_SBISmallcap!B5 -> 45658 | C640: =SIP_Fund3_SBISmallcap!C5 -> 3000 | D640: =SIP_Fund3_SBISmallcap!H5 -> 149 | E640: =SIP_Fund3_SBISmallcap!I5 -> 20.134228 | F640: =Assumptions!$C$5-B640 -> 4031 | G640: =Assumptions!$D$24*(1+Assumptions!$F$24)^((Assumptions!$C$5-Assumptions!$C$4)/365) -> 646.34026 | H640: =E640*G640 -> 13013.562 | I640: =IF(F640<365,Assumptions!$G$24,IF(F640<=730,Assumptions!$H$24,Assumptions!$I$24)) -> 0 | J640: =H640*I640 -> 0 | K640: =H640-J640 -> 13013.562 | L640: =K640-C640 -> 10013.562 | M640: =IF(F640>365,"LTCG","STCG") -> LTCG | N640: =IF(M640="LTCG",Assumptions!$C$12,Assumptions!$C$11) -> 0.125 | O640: =IF(M640="STCG",MAX(L640,0)*Assumptions!$C$11,"agg. below") -> agg. below
A641: =TEXT(SIP_Fund3_SBISmallcap!B6,"mmm-yyyy") -> Feb-2025 | B641: =SIP_Fund3_SBISmallcap!B6 -> 45689 | C641: =SIP_Fund3_SBISmallcap!C6 -> 3000 | D641: =SIP_Fund3_SBISmallcap!H6 -> 150.69095 | E641: =SIP_Fund3_SBISmallcap!I6 -> 19.908296 | F641: =Assumptions!$C$5-B641 -> 4000 | G641: =Assumptions!$D$24*(1+Assumptions!$F$24)^((Assumptions!$C$5-Assumptions!$C$4)/365) -> 646.34026 | H641: =E641*G641 -> 12867.533 | I641: =IF(F641<365,Assumptions!$G$24,IF(F641<=730,Assumptions!$H$24,Assumptions!$I$24)) -> 0 | J641: =H641*I641 -> 0 | K641: =H641-J641 -> 12867.533 | L641: =K641-C641 -> 9867.5332 | M641: =IF(F641>365,"LTCG","STCG") -> LTCG | N641: =IF(M641="LTCG",Assumptions!$C$12,Assumptions!$C$11) -> 0.125 | O641: =IF(M641="STCG",MAX(L641,0)*Assumptions!$C$11,"agg. below") -> agg. below
A642: =TEXT(SIP_Fund3_SBISmallcap!B7,"mmm-yyyy") -> Mar-2025 | B642: =SIP_Fund3_SBISmallcap!B7 -> 45717 | C642: =SIP_Fund3_SBISmallcap!C7 -> 3000 | D642: =SIP_Fund3_SBISmallcap!H7 -> 152.23475 | E642: =SIP_Fund3_SBISmallcap!I7 -> 19.706408 | F642: =Assumptions!$C$5-B642 -> 3972 | G642: =Assumptions!$D$24*(1+Assumptions!$F$24)^((Assumptions!$C$5-Assumptions!$C$4)/365) -> 646.34026 | H642: =E642*G642 -> 12737.045 | I642: =IF(F642<365,Assumptions!$G$24,IF(F642<=730,Assumptions!$H$24,Assumptions!$I$24)) -> 0 | J642: =H642*I642 -> 0 | K642: =H642-J642 -> 12737.045 | L642: =K642-C642 -> 9737.0449 | M642: =IF(F642>365,"LTCG","STCG") -> LTCG | N642: =IF(M642="LTCG",Assumptions!$C$12,Assumptions!$C$11) -> 0.125 | O642: =IF(M642="STCG",MAX(L642,0)*Assumptions!$C$11,"agg. below") -> agg. below
A643: =TEXT(SIP_Fund3_SBISmallcap!B8,"mmm-yyyy") -> Apr-2025 | B643: =SIP_Fund3_SBISmallcap!B8 -> 45748 | C643: =SIP_Fund3_SBISmallcap!C8 -> 3000 | D643: =SIP_Fund3_SBISmallcap!H8 -> 153.9624 | E643: =SIP_Fund3_SBISmallcap!I8 -> 19.485276 | F643: =Assumptions!$C$5-B643 -> 3941 | G643: =Assumptions!$D$24*(1+Assumptions!$F$24)^((Assumptions!$C$5-Assumptions!$C$4)/365) -> 646.34026 | H643: =E643*G643 -> 12594.119 | I643: =IF(F643<365,Assumptions!$G$24,IF(F643<=730,Assumptions!$H$24,Assumptions!$I$24)) -> 0 | J643: =H643*I643 -> 0 | K643: =H643-J643 -> 12594.119 | L643: =K643-C643 -> 9594.1187 | M643: =IF(F643>365,"LTCG","STCG") -> LTCG | N643: =IF(M643="LTCG",Assumptions!$C$12,Assumptions!$C$11) -> 0.125 | O643: =IF(M643="STCG",MAX(L643,0)*Assumptions!$C$11,"agg. below") -> agg. below
A644: =TEXT(SIP_Fund3_SBISmallcap!B9,"mmm-yyyy") -> May-2025 | B644: =SIP_Fund3_SBISmallcap!B9 -> 45778 | C644: =SIP_Fund3_SBISmallcap!C9 -> 3000 | D644: =SIP_Fund3_SBISmallcap!H9 -> 155.653 | E644: =SIP_Fund3_SBISmallcap!I9 -> 19.273641 | F644: =Assumptions!$C$5-B644 -> 3911 | G644: =Assumptions!$D$24*(1+Assumptions!$F$24)^((Assumptions!$C$5-Assumptions!$C$4)/365) -> 646.34026 | H644: =E644*G644 -> 12457.33 | I644: =IF(F644<365,Assumptions!$G$24,IF(F644<=730,Assumptions!$H$24,Assumptions!$I$24)) -> 0 | J644: =H644*I644 -> 0 | K644: =H644-J644 -> 12457.33 | L644: =K644-C644 -> 9457.3302 | M644: =IF(F644>365,"LTCG","STCG") -> LTCG | N644: =IF(M644="LTCG",Assumptions!$C$12,Assumptions!$C$11) -> 0.125 | O644: =IF(M644="STCG",MAX(L644,0)*Assumptions!$C$11,"agg. below") -> agg. below
A645: =TEXT(SIP_Fund3_SBISmallcap!B10,"mmm-yyyy") -> Jun-2025 | B645: =SIP_Fund3_SBISmallcap!B10 -> 45809 | C645: =SIP_Fund3_SBISmallcap!C10 -> 3000 | D645: =SIP_Fund3_SBISmallcap!H10 -> 157.41945 | E645: =SIP_Fund3_SBISmallcap!I10 -> 19.057366 | F645: =Assumptions!$C$5-B645 -> 3880 | G645: =Assumptions!$D$24*(1+Assumptions!$F$24)^((Assumptions!$C$5-Assumptions!$C$4)/365) -> 646.34026 | H645: =E645*G645 -> 12317.543 | I645: =IF(F645<365,Assumptions!$G$24,IF(F645<=730,Assumptions!$H$24,Assumptions!$I$24)) -> 0 | J645: =H645*I645 -> 0 | K645: =H645-J645 -> 12317.543 | L645: =K645-C645 -> 9317.5427 | M645: =IF(F645>365,"LTCG","STCG") -> LTCG | N645: =IF(M645="LTCG",Assumptions!$C$12,Assumptions!$C$11) -> 0.125 | O645: =IF(M645="STCG",MAX(L645,0)*Assumptions!$C$11,"agg. below") -> agg. below
...

Sheet 10Yr_Summary
A1: 10-Year Outcome (Jan-2025 – Dec-2034): Direct vs Regular
A2: Same SIP plan, same fund manager, same portfolio — only the plan (and its cost) differs
A4: Fund | B4: Category | C4: Total Invested (₹) | D4: Direct — Final Value (₹) | E4: Regular — Final Value (₹) | F4: Commission/Cost Gap (₹) | G4: Cost as % of Direct Value | H4: Jan-2036 Net Received — Direct (₹) | I4: Jan-2036 Net Received — Regular (₹)
A5: Parag Parikh Flexi Cap Fund | B5: Flexi Cap | C5: =SIP_Fund1_PPFAS!L124 -> 900000 | D5: =SIP_Fund1_PPFAS!G124 -> 1461867.7 | E5: =SIP_Fund1_PPFAS!K124 -> 1430285.4 | F5: =D5-E5 -> 31582.322 | G5: =F5/D5 -> 0.02160409 | H5: =Withdrawal_Jan2036!O128 -> 1579536.6 | I5: =Withdrawal_Jan2036!O253 -> 1540749.5
A6: HDFC Mid-Cap Opportunities Fund | B6: Mid Cap | C6: =SIP_Fund2_HDFCMidcap!L124 -> 900000 | D6: =SIP_Fund2_HDFCMidcap!G124 -> 1590928.9 | E6: =SIP_Fund2_HDFCMidcap!K124 -> 1558819.2 | F6: =D6-E6 -> 32109.751 | G6: =F6/D6 -> 0.02018302 | H6: =Withdrawal_Jan2036!O382 -> 1740920.7 | I6: =Withdrawal_Jan2036!O507 -> 1700897.5
A7: SBI Small Cap Fund | B7: Small Cap | C7: =SIP_Fund3_SBISmallcap!L124 -> 900000 | D7: =SIP_Fund3_SBISmallcap!G124 -> 1660239.1 | E7: =SIP_Fund3_SBISmallcap!K124 -> 1605210.4 | F7: =D7-E7 -> 55028.673 | G7: =F7/D7 -> 0.03314503 | H7: =Withdrawal_Jan2036!O636 -> 1827776.2 | I7: =Withdrawal_Jan2036!O761 -> 1758766
A9: Reminder: figures above come from ILLUSTRATIVE assumed annual returns (Assumptions sheet), not a promise of what these funds will actually return. Change the CAGR assumptions to stress-test the story.

Sheet STP_Illustration
A1: STP — Phasing a Lumpsum Into Equity
A2: ₹5,00,000 moved from a debt/liquid fund into Parag Parikh Flexi Cap (Direct) over 10 months, vs investing it all on Day 1
A4: Month # | B4: Transfer Date | C4: Source — Opening Bal. (₹) | D4: Transfer Out (₹) | E4: Source — Bal. After Transfer (₹) | F4: Source — Growth (₹) | G4: Source — Closing Bal. (₹) | H4: Destination NAV (₹) | I4: Units Bought | J4: Cum. Units | K4: Destination Value (₹)
A5: 1 | B5: =Assumptions!$C$30 -> 45658 | C5: =Assumptions!$C$28 -> 500000 | D5: =Assumptions!$C$28/Assumptions!$C$29 -> 50000 | E5: =C5-D5 -> 450000 | F5: =E5*((1+Assumptions!$C$31)^(1/12)-1) -> 2367.7624 | G5: =E5+F5 -> 452367.76 | H5: =Assumptions!$D$19*(1+Assumptions!$F$19)^((B5-Assumptions!$C$4)/365) -> 75 | I5: =D5/H5 -> 666.66667 | J5: =I5 -> 666.66667 | K5: =J5*H5 -> 50000
A6: 2 | B6: =EDATE(B5,1) -> 45689 | C6: =G5 -> 452367.76 | D6: =Assumptions!$C$28/Assumptions!$C$29 -> 50000 | E6: =C6-D6 -> 402367.76 | F6: =E6*((1+Assumptions!$C$31)^(1/12)-1) -> 2117.1362 | G6: =E6+F6 -> 404484.9 | H6: =Assumptions!$D$19*(1+Assumptions!$F$19)^((B6-Assumptions!$C$4)/365) -> 75.725374 | I6: =D6/H6 -> 660.28067 | J6: =J5+I6 -> 1326.9473 | K6: =J6*H6 -> 100483.58
A7: 3 | B7: =EDATE(B6,1) -> 45717 | C7: =G6 -> 404484.9 | D7: =Assumptions!$C$28/Assumptions!$C$29 -> 50000 | E7: =C7-D7 -> 354484.9 | F7: =E7*((1+Assumptions!$C$31)^(1/12)-1) -> 1865.1912 | G7: =E7+F7 -> 356350.09 | H7: =Assumptions!$D$19*(1+Assumptions!$F$19)^((B7-Assumptions!$C$4)/365) -> 76.386578 | I7: =D7/H7 -> 654.56526 | J7: =J6+I7 -> 1981.5126 | K7: =J7*H7 -> 151360.97
A8: 4 | B8: =EDATE(B7,1) -> 45748 | C8: =G7 -> 356350.09 | D8: =Assumptions!$C$28/Assumptions!$C$29 -> 50000 | E8: =C8-D8 -> 306350.09 | F8: =E8*((1+Assumptions!$C$31)^(1/12)-1) -> 1611.9205 | G8: =E8+F8 -> 307962.01 | H8: =Assumptions!$D$19*(1+Assumptions!$F$19)^((B8-Assumptions!$C$4)/365) -> 77.125362 | I8: =D8/H8 -> 648.29518 | J8: =J7+I8 -> 2629.8078 | K8: =J8*H8 -> 202824.88
A9: 5 | B9: =EDATE(B8,1) -> 45778 | C9: =G8 -> 307962.01 | D9: =Assumptions!$C$28/Assumptions!$C$29 -> 50000 | E9: =C9-D9 -> 257962.01 | F9: =E9*((1+Assumptions!$C$31)^(1/12)-1) -> 1357.3172 | G9: =E9+F9 -> 259319.33 | H9: =Assumptions!$D$19*(1+Assumptions!$F$19)^((B9-Assumptions!$C$4)/365) -> 77.847117 | I9: =D9/H9 -> 642.28455 | J9: =J8+I9 -> 3272.0923 | K9: =J9*H9 -> 254722.95
A10: 6 | B10: =EDATE(B9,1) -> 45809 | C10: =G9 -> 259319.33 | D10: =Assumptions!$C$28/Assumptions!$C$29 -> 50000 | E10: =C10-D10 -> 209319.33 | F10: =E10*((1+Assumptions!$C$31)^(1/12)-1) -> 1101.3743 | G10: =E10+F10 -> 210420.7 | H10: =Assumptions!$D$19*(1+Assumptions!$F$19)^((B10-Assumptions!$C$4)/365) -> 78.600026 | I10: =D10/H10 -> 636.1321 | J10: =J9+I10 -> 3908.2244 | K10: =J10*H10 -> 307186.54
A11: 7 | B11: =EDATE(B10,1) -> 45839 | C11: =G10 -> 210420.7 | D11: =Assumptions!$C$28/Assumptions!$C$29 -> 50000 | E11: =C11-D11 -> 160420.7 | F11: =E11*((1+Assumptions!$C$31)^(1/12)-1) -> 844.08469 | G11: =E11+F11 -> 161264.79 | H11: =Assumptions!$D$19*(1+Assumptions!$F$19)^((B11-Assumptions!$C$4)/365) -> 79.335581 | I11: =D11/H11 -> 630.23424 | J11: =J10+I11 -> 4538.4587 | K11: =J11*H11 -> 360061.26
A12: 8 | B12: =EDATE(B11,1) -> 45870 | C12: =G11 -> 161264.79 | D12: =Assumptions!$C$28/Assumptions!$C$29 -> 50000 | E12: =C12-D12 -> 111264.79 | F12: =E12*((1+Assumptions!$C$31)^(1/12)-1) -> 585.44129 | G12: =E12+F12 -> 111850.23 | H12: =Assumptions!$D$19*(1+Assumptions!$F$19)^((B12-Assumptions!$C$4)/365) -> 80.102887 | I12: =D12/H12 -> 624.19723 | J12: =J11+I12 -> 5162.6559 | K12: =J12*H12 -> 413543.64
A13: 9 | B13: =EDATE(B12,1) -> 45901 | C13: =G12 -> 111850.23 | D13: =Assumptions!$C$28/Assumptions!$C$29 -> 50000 | E13: =C13-D13 -> 61850.228 | F13: =E13*((1+Assumptions!$C$31)^(1/12)-1) -> 325.43699 | G13: =E13+F13 -> 62175.665 | H13: =Assumptions!$D$19*(1+Assumptions!$F$19)^((B13-Assumptions!$C$4)/365) -> 80.877614 | I13: =D13/H13 -> 618.21804 | J13: =J12+I13 -> 5780.8739 | K13: =J13*H13 -> 467543.29
A14: 10 | B14: =EDATE(B13,1) -> 45931 | C14: =G13 -> 62175.665 | D14: =Assumptions!$C$28/Assumptions!$C$29 -> 50000 | E14: =C14-D14 -> 12175.665 | F14: =E14*((1+Assumptions!$C$31)^(1/12)-1) -> 64.064626 | G14: =E14+F14 -> 12239.729 | H14: =Assumptions!$D$19*(1+Assumptions!$F$19)^((B14-Assumptions!$C$4)/365) -> 81.634483 | I14: =D14/H14 -> 612.48627 | J14: =J13+I14 -> 6393.3602 | K14: =J14*H14 -> 521918.65
A16: Total transferred (₹) | D16: =SUM(D5:D14) -> 500000
A17: STP approach — destination value at end of transfer window (₹) | D17: =K14 -> 521918.65
A18: If invested as lumpsum on Day 1 instead — value on the same end date (₹) | D18: =(Assumptions!$C$28/H5)*H14 -> 544229.89
A19: STP result vs Day-1 lumpsum (₹) | D19: =D17-D18 -> -22311.233
A21: Why this matters (read before presenting): this model uses a smooth, steadily-rising NAV path (a constant assumed CAGR), so a Day-1 lumpsum will almost always out-produce an STP here — there is no dip for the STP to average into. In real markets, which move up and down, STP's actual value shows up precisely when the market dips during the transfer window: phasing in means part of your money buys at the lower, dipped NAV instead of all of it going in right before a fall. Use this sheet to teach the MECHANICS of STP (how units, NAV and the source-to-destination transfer work), not as proof that STP beats or loses to lumpsum — that depends entirely on the market path, which nobody can predict in advance.

Sheet SWP_Illustration
A1: SWP — Drawing an Income From the Corpus
A2: ₹25,000/month withdrawn from the Fund 1 (Parag Parikh Flexi Cap, Direct) corpus for 5 years, starting the month after the 10-year SIP ends
A4: Starting Corpus (Fund 1 Direct value on the last SIP date, Dec-2034) | E4: =SIP_Fund1_PPFAS!G124 -> 1461867.7
A6: Month # | B6: Date | C6: Opening Balance (₹) | D6: Growth This Month (₹) | E6: Balance After Growth (₹) | F6: Withdrawal Taken (₹) | G6: Closing Balance (₹) | H6: Cumulative Withdrawn (₹)
A7: 1 | B7: =Assumptions!$C$33 -> 49310 | C7: =$E$4 -> 1461867.7 | D7: =C7*((1+Assumptions!$C$35)^(1/12)-1) -> 13871.36 | E7: =C7+D7 -> 1475739.1 | F7: =MIN(Assumptions!$C$32,E7) -> 25000 | G7: =E7-F7 -> 1450739.1 | H7: =F7 -> 25000
A8: 2 | B8: =EDATE(B7,1) -> 49341 | C8: =G7 -> 1450739.1 | D8: =C8*((1+Assumptions!$C$35)^(1/12)-1) -> 13765.763 | E8: =C8+D8 -> 1464504.8 | F8: =MIN(Assumptions!$C$32,E8) -> 25000 | G8: =E8-F8 -> 1439504.8 | H8: =H7+F8 -> 50000
A9: 3 | B9: =EDATE(B8,1) -> 49369 | C9: =G8 -> 1439504.8 | D9: =C9*((1+Assumptions!$C$35)^(1/12)-1) -> 13659.163 | E9: =C9+D9 -> 1453164 | F9: =MIN(Assumptions!$C$32,E9) -> 25000 | G9: =E9-F9 -> 1428164 | H9: =H8+F9 -> 75000
A10: 4 | B10: =EDATE(B9,1) -> 49400 | C10: =G9 -> 1428164 | D10: =C10*((1+Assumptions!$C$35)^(1/12)-1) -> 13551.552 | E10: =C10+D10 -> 1441715.6 | F10: =MIN(Assumptions!$C$32,E10) -> 25000 | G10: =E10-F10 -> 1416715.6 | H10: =H9+F10 -> 100000
A11: 5 | B11: =EDATE(B10,1) -> 49430 | C11: =G10 -> 1416715.6 | D11: =C11*((1+Assumptions!$C$35)^(1/12)-1) -> 13442.921 | E11: =C11+D11 -> 1430158.5 | F11: =MIN(Assumptions!$C$32,E11) -> 25000 | G11: =E11-F11 -> 1405158.5 | H11: =H10+F11 -> 125000
A12: 6 | B12: =EDATE(B11,1) -> 49461 | C12: =G11 -> 1405158.5 | D12: =C12*((1+Assumptions!$C$35)^(1/12)-1) -> 13333.258 | E12: =C12+D12 -> 1418491.7 | F12: =MIN(Assumptions!$C$32,E12) -> 25000 | G12: =E12-F12 -> 1393491.7 | H12: =H11+F12 -> 150000
A13: 7 | B13: =EDATE(B12,1) -> 49491 | C13: =G12 -> 1393491.7 | D13: =C13*((1+Assumptions!$C$35)^(1/12)-1) -> 13222.555 | E13: =C13+D13 -> 1406714.3 | F13: =MIN(Assumptions!$C$32,E13) -> 25000 | G13: =E13-F13 -> 1381714.3 | H13: =H12+F13 -> 175000
A14: 8 | B14: =EDATE(B13,1) -> 49522 | C14: =G13 -> 1381714.3 | D14: =C14*((1+Assumptions!$C$35)^(1/12)-1) -> 13110.801 | E14: =C14+D14 -> 1394825.1 | F14: =MIN(Assumptions!$C$32,E14) -> 25000 | G14: =E14-F14 -> 1369825.1 | H14: =H13+F14 -> 200000
A15: 9 | B15: =EDATE(B14,1) -> 49553 | C15: =G14 -> 1369825.1 | D15: =C15*((1+Assumptions!$C$35)^(1/12)-1) -> 12997.987 | E15: =C15+D15 -> 1382823.1 | F15: =MIN(Assumptions!$C$32,E15) -> 25000 | G15: =E15-F15 -> 1357823.1 | H15: =H14+F15 -> 225000
A16: 10 | B16: =EDATE(B15,1) -> 49583 | C16: =G15 -> 1357823.1 | D16: =C16*((1+Assumptions!$C$35)^(1/12)-1) -> 12884.102 | E16: =C16+D16 -> 1370707.2 | F16: =MIN(Assumptions!$C$32,E16) -> 25000 | G16: =E16-F16 -> 1345707.2 | H16: =H15+F16 -> 250000
A17: 11 | B17: =EDATE(B16,1) -> 49614 | C17: =G16 -> 1345707.2 | D17: =C17*((1+Assumptions!$C$35)^(1/12)-1) -> 12769.137 | E17: =C17+D17 -> 1358476.3 | F17: =MIN(Assumptions!$C$32,E17) -> 25000 | G17: =E17-F17 -> 1333476.3 | H17: =H16+F17 -> 275000
A18: 12 | B18: =EDATE(B17,1) -> 49644 | C18: =G17 -> 1333476.3 | D18: =C18*((1+Assumptions!$C$35)^(1/12)-1) -> 12653.081 | E18: =C18+D18 -> 1346129.4 | F18: =MIN(Assumptions!$C$32,E18) -> 25000 | G18: =E18-F18 -> 1321129.4 | H18: =H17+F18 -> 300000
A19: 13 | B19: =EDATE(B18,1) -> 49675 | C19: =G18 -> 1321129.4 | D19: =C19*((1+Assumptions!$C$35)^(1/12)-1) -> 12535.923 | E19: =C19+D19 -> 1333665.3 | F19: =MIN(Assumptions!$C$32,E19) -> 25000 | G19: =E19-F19 -> 1308665.3 | H19: =H18+F19 -> 325000
... A66: 60 | B66: =EDATE(B65,1) -> 51105 | C66: =G65 -> 587206.76 | D66: =C66*((1+Assumptions!$C$35)^(1/12)-1) -> 5571.8833 | E66: =C66+D66 -> 592778.64 | F66: =MIN(Assumptions!$C$32,E66) -> 25000 | G66: =E66-F66 -> 567778.64 | H66: =H65+F66 -> 1500000
A68: After 5 years (60 months):
A69: Total withdrawn (₹) | C69: =H66 -> 1500000
A70: Corpus remaining (₹) | C70: =G66 -> 567778.64
A72: Simplified for teaching: withdrawals are shown gross, without a per-withdrawal capital-gains tax deduction. In reality each SWP instalment redeems units and triggers a capital gain exactly like the lots in the Withdrawal_Jan2036 sheet — since this corpus is over 3 years old by the time SWP starts, most/all of it would qualify for LTCG (12.5% above the ₹1,25,000/year exemption). Reduce the withdrawal amount by an estimated tax drag if you want to show a more conservative, net-of-tax number live.
